{
  "content": [
    {
      "asset": "DGDG",
      "type": "primary",
      "data": "ਜਾਇ ਸਕੈ ਹਟਿਹੂੰ ਨ ਰਹੈ; ਮਤਵਾਰੇ ਕੀ ਭਾਤਿ ਡਿਗੈ ਡਗ ਡਾਰੈ ॥੧੨॥",
      "page": 971
    },
    {
      "asset": "DSKO",
      "type": "translation",
      "language": "en",
      "data": "Also as, on the one hand he was dreaded and, on the other, there was the lover’s allurement.(12)"
    },
    {
      "asset": "RSJD",
      "type": "translation",
      "language": "pa",
      "data": "ਉਹ ਨਾ ਉਥੇ ਜਾ ਸਕਦਾ ਹੈ, ਨਾ ਰਹਿ ਸਕਦਾ ਹੈ, ਮਤਵਾਲੇ ਵਾਂਗ ਡਿਗਡੋਲੇ ਖਾਂਦਾ ਤੁਰ ਰਿਹਾ ਹੈ ॥੧੨॥"
    }
  ]
}