{
  "content": [
    {
      "asset": "ssa2",
      "type": "primary",
      "data": "ਰਾਖਿ ਲੀਨੋ; ਸਭੁ ਜਨ ਕਾ ਪੜਦਾ ॥",
      "page": 1145,
      "line": 1
    },
    {
      "asset": "sbms",
      "type": "translation",
      "language": "en",
      "data": "He, who covered up His slave's all shame."
    },
    {
      "asset": "sbms",
      "type": "translation",
      "language": "pa",
      "data": "ਜਿਸ ਨੇ ਆਪਣੇ ਗੋਲੇ ਦੇ ਸਾਰੇ ਐਬ ਕੱਜ ਲਏ ਹਨ।"
    },
    {
      "asset": "dssk",
      "type": "translation",
      "language": "en",
      "data": "He covers the faults of His humble servant."
    },
    {
      "asset": "nkft",
      "type": "translation",
      "language": "pa",
      "data": "ਸਰਬ ਪ੍ਰਕਾਰ ਦਾਸ ਕਾ ਪੜਦਾ ਪਰਮੇਸ੍ਵਰ ਨੇ ਰਖ ਲੀਆ ਹੈ॥"
    },
    {
      "asset": "psst",
      "type": "translation",
      "language": "pa",
      "data": "ਆਪਣੇ ਸੇਵਕ ਦੀ ਇੱਜ਼ਤ ਪਰਮਾਤਮਾ ਹਰ ਥਾਂ ਰੱਖ ਲੈਂਦਾ ਹੈ,"
    },
    {
      "asset": "snst",
      "type": "translation",
      "language": "es",
      "data": "Y es sólo Dios Quien cubre mi vergüenza,"
    }
  ]
}