[
  {
    "shabad_id": 10456,
    "pada": null,
    "source_line": 1,
    "gurmukhi": "innMd gyd biR`dXM ]AKyd nwd du`DrM ]",
    "transliteration": "Ninand Get Briddayan|| Akhed Naad Duddharan||",
    "translation": "Thou art radiant like the great ball of the Sun; beyond the tunes of worldly joys.",
    "punjabi": "",
    "pronunciation": null,
    "type_id": 0
  },
  {
    "shabad_id": 10456,
    "pada": null,
    "source_line": 2,
    "gurmukhi": "AT`t b`t b`tkM ]AG`t An`t su`KlM ]4]82]",
    "transliteration": "Athatt Batt Battakan|| Aghatt Anatt Soukkhalan||4||82||",
    "translation": "Thou art everlasting like the Bunyan-seed; and art Blissful ever perfectly.4.82.",
    "punjabi": "",
    "pronunciation": null,
    "type_id": 0
  },
  {
    "shabad_id": 10456,
    "pada": null,
    "source_line": 3,
    "gurmukhi": "AKu`t qu`t diR`bkM ]Aju`t Cu`t su`CkM ]",
    "transliteration": "Akhoutt Toutt Dribbakan|| Ajoutt Chhoutt Souchchhakan||",
    "translation": "The Treasure of Thy wealth is inexhaustible; O Immaculate Lord! Thou art not united with anyone.",
    "punjabi": "",
    "pronunciation": null,
    "type_id": 0
  },
  {
    "shabad_id": 10456,
    "pada": null,
    "source_line": 4,
    "gurmukhi": "AGu`t qu`t AwsnM ]AlyK AByK AnwsnM ]5]83]",
    "transliteration": "Aghoutt Toutt Aasanan|| Alekh Abhekh Anaasanan||5||83||",
    "translation": "Thy seat is eternal; Thou art accountless, guiseless and Imperishable.5.83.",
    "punjabi": "",
    "pronunciation": null,
    "type_id": 0
  },
  {
    "shabad_id": 10456,
    "pada": null,
    "source_line": 5,
    "gurmukhi": "suBMq dMq pdukM ]jlMq swm su GtM ]",
    "transliteration": "Soubhant Dant Padoukan|| Jalant Saam Su Ghataaag||",
    "translation": "The row of thy teeth looks graceful; seeing which the dark clouds feel jealous.",
    "punjabi": "",
    "pronunciation": null,
    "type_id": 0
  },
  {
    "shabad_id": 10456,
    "pada": null,
    "source_line": 6,
    "gurmukhi": "suBMq CudR GMtkw ]jlMq Bwrk Ctw ]6]84]",
    "transliteration": "Soubhant Chhudra Ghantakaa|| Jalant Bhaarak Chhataa||6||84||",
    "translation": "The small bells look elegant in the string round Thy waist; seeing Thy effulgence the splendour of the Sun feels jealous.6.84.",
    "punjabi": "",
    "pronunciation": null,
    "type_id": 0
  },
  {
    "shabad_id": 10456,
    "pada": null,
    "source_line": 7,
    "gurmukhi": "isrI su sIs su`BIXM ]Gtwk bwn au`BIXM ]",
    "transliteration": "Sirisu Sees Soubbheeyan|| Ghatek Baan Oubbheeyan||",
    "translation": "The crest on Thy head seems splendid; like the shaft high up in the clouds.",
    "punjabi": "",
    "pronunciation": null,
    "type_id": 0
  },
  {
    "shabad_id": 10456,
    "pada": null,
    "source_line": 8,
    "gurmukhi": "suBMq sIs isDrM ]jlMq is`DrI nrM ]7]85]",
    "transliteration": "Soubhant Sees Sidharan|| Jalant Siddharinaran||7||85||",
    "translation": "The Crown on Thy head looks elegant; seeing which the moon feels shy.7.85.",
    "punjabi": "",
    "pronunciation": null,
    "type_id": 0
  },
  {
    "shabad_id": 10456,
    "pada": null,
    "source_line": 9,
    "gurmukhi": "clMq dMq p`qkM ]BjMq dyiK du dlM ]",
    "transliteration": "Chalant Dant Pattakan|| Bhajant Dekh(i) Du Dalan||",
    "translation": "The rows of demons are moving; and both the armies are running.",
    "punjabi": "",
    "pronunciation": null,
    "type_id": 0
  },
  {
    "shabad_id": 10456,
    "pada": null,
    "source_line": 10,
    "gurmukhi": "qjMq ssqR AsqRkM ]clMq c`kR cau idsM ]8]86]",
    "transliteration": "Tajant Sastra Astrakan|| Chalant Chakkra Chau Disan||8||86||",
    "translation": "When Thou usest Thy arms and weapons; and Thy disc moves in all the four directions.8.86.",
    "punjabi": "",
    "pronunciation": null,
    "type_id": 0
  },
  {
    "shabad_id": 10456,
    "pada": null,
    "source_line": 11,
    "gurmukhi": "AgMm qyj soBIXM ]irKIs eIs loBIXM ]",
    "transliteration": "Agadm Tej Sobheeyan|| Rikhees Ees Lobheeyan||",
    "translation": "Thy Inaccesible Glory looks elegant; therefore the great sages and Shiva are covetous to have Thy Sight.",
    "punjabi": "",
    "pronunciation": null,
    "type_id": 0
  },
  {
    "shabad_id": 10456,
    "pada": null,
    "source_line": 12,
    "gurmukhi": "Anyk bwr iDAwvhI ]n qqR pwr pwvhI ]9]87]",
    "transliteration": "Anek Baar Dhiaavahee|| Na Tatra Paar Paavahee||9||87||",
    "translation": "They remember Thy Name many times; even then they have not been able go know Thy limits.9.87.",
    "punjabi": "",
    "pronunciation": null,
    "type_id": 0
  },
  {
    "shabad_id": 10456,
    "pada": null,
    "source_line": 13,
    "gurmukhi": "ADo su DUm DUm hI ]AGUr nyqR GUm hI ]",
    "transliteration": "Adho Su Dhoom Dhoom Hee|| Aghoor Netra Ghoom Hee||",
    "translation": "Many with faces upside down light the fire; many ascetics roam forsaking their sleep.",
    "punjabi": "",
    "pronunciation": null,
    "type_id": 0
  },
  {
    "shabad_id": 10456,
    "pada": null,
    "source_line": 14,
    "gurmukhi": "su pMc Agn swDIXM ]n qwm pwr lwDIXM ]10]88]",
    "transliteration": "Su Panch Agad Saadheeyan|| Na Taam Paar Laadheeyan||10||88||",
    "translation": "Many perform austerity of five fires; even they have not been able to know thy limits.10.88.",
    "punjabi": "",
    "pronunciation": null,
    "type_id": 0
  }
]