[
  {
    "id": "MNX",
    "sttm_id": 1585,
    "writer": "Guru Arjan Dev Ji",
    "section": "Raag Aasaa",
    "subsection": null,
    "lines": [
      {
        "id": "3LS9",
        "source_page": 408,
        "source_line": 2,
        "pronunciation": "",
        "pronunciation_information": "",
        "type": "Sirlekh",
        "gurmukhi": {
          "SGPC": "Awsw mhlw 5 ]"
        },
        "translations": {
          "English": {
            "Dr. Sant Singh Khalsa": {
              "translation": "Aasaa, Fifth Mehl:",
              "additional_information": {}
            },
            "Bhai Manmohan Singh": {
              "translation": "Asa 5th Guru.",
              "additional_information": {}
            }
          },
          "Punjabi": {
            "Bhai Manmohan Singh": {
              "translation": "ਆਸਾ ਪੰਜਵੀਂ ਪਾਤਸ਼ਾਹੀ।",
              "additional_information": {}
            },
            "Fareedkot Teeka": {
              "translation": "",
              "additional_information": {
                "reference": ""
              }
            },
            "Prof. Sahib Singh": {
              "translation": "ਰਾਗ ਆਸਾ ਵਿੱਚ ਗੁਰੂ ਅਰਜਨਦੇਵ ਜੀ ਦੀ ਬਾਣੀ।",
              "additional_information": {
                "arth": "",
                "note": ""
              }
            }
          },
          "Spanish": {
            "SikhNet": {
              "translation": "Asa, Mejl Guru Aryan, Quinto Canal Divino.",
              "additional_information": {}
            }
          }
        }
      },
      {
        "id": "9L4Z",
        "source_page": 408,
        "source_line": 2,
        "pronunciation": "",
        "pronunciation_information": "",
        "type": "Rahao",
        "gurmukhi": {
          "SGPC": "imlu rwm ipAwry; qum ibnu DIrju. ko n krY ]1] rhwau ]"
        },
        "translations": {
          "English": {
            "Dr. Sant Singh Khalsa": {
              "translation": "Please, come to me, O Beloved Lord; without You, no one can comfort me. ||1||Pause||",
              "additional_information": {}
            },
            "Bhai Manmohan Singh": {
              "translation": "Meet me my Beloved Lord, without Thee no one gives me consolation. Pause.",
              "additional_information": {}
            }
          },
          "Punjabi": {
            "Bhai Manmohan Singh": {
              "translation": "ਮੇਰੇ ਪ੍ਰੀਤਮ ਪ੍ਰਭੂ! ਮੈਨੂੰ ਦਰਸ਼ਨ ਦੇ, ਤੇਰੇ ਬਗੈਰ ਮੈਨੂੰ ਕੋਈ ਦਿਲਾਸਾ ਨਹੀਂ ਦਿੰਦਾ। ਠਹਿਰਾਉ।",
              "additional_information": {}
            },
            "Fareedkot Teeka": {
              "translation": "ਹੇ ਰਾਮ ਪ੍ਯਾਰੇ ਮਿਲਹੁ! ਤੁਮਾਰੇ ਬਿਨਾਂ (ਧੀਰਜੁ) ਦਿਲਾਸਾ ਮੈਨੂੰ ਔਰ ਕੋਈ ਨਹੀਂ ਦੇਨਾ ਕਰਤਾ ਹੈ ਵਾ ਤੇਰੀ ਪ੍ਰਾਪਤੀ ਬਿਨਾਂ ਕੋਈ ਧੀਰਜ ਨਹੀਂ ਕਰਤਾ ਹੈ॥੧॥ ਰਹਾਉ ॥",
              "additional_information": {
                "reference": ""
              }
            },
            "Prof. Sahib Singh": {
              "translation": "ਹੇ ਮੇਰੇ ਪਿਆਰੇ ਰਾਮ! (ਮੈਨੂੰ) ਮਿਲ! ਤੇਰੇ ਮਿਲਾਪ ਤੋਂ ਬਿਨਾ ਹੋਰ ਕੋਈ ਭੀ (ਉੱਦਮ) ਮੇਰੇ ਮਨ ਵਿਚ ਸ਼ਾਂਤੀ ਪੈਦਾ ਨਹੀਂ ਕਰ ਸਕਦਾ ॥੧॥ ਰਹਾਉ ॥",
              "additional_information": {
                "arth": "ਰਾਮ = ਹੇ ਰਾਮ। ਧੀਰਜੁ = ਸ਼ਾਂਤੀ। ਕੋ = ਹੋਰ ਕੋਈ ਭੀ ॥੧॥ ਰਹਾਉ ॥",
                "note": ""
              }
            }
          },
          "Spanish": {
            "SikhNet": {
              "translation": "Oh Señor Querido, ven conmigo; sin Ti, nadie está tranquilo. (1‑Pausa)",
              "additional_information": {}
            }
          }
        }
      },
      {
        "id": "210B",
        "source_page": 408,
        "source_line": 3,
        "pronunciation": "",
        "pronunciation_information": "",
        "type": "Pankti",
        "gurmukhi": {
          "SGPC": "isMimRiq swsqR bhu krm kmwey; pRB qumry drs ibnu; suKu nwhI ]1]"
        },
        "translations": {
          "English": {
            "Dr. Sant Singh Khalsa": {
              "translation": "One may read the Simritees and the Shaastras, and perform all sorts of religious rituals; and yet, without the Blessed Vision of Your Darshan, God, there is no peace at all. ||1||",
              "additional_information": {}
            },
            "Bhai Manmohan Singh": {
              "translation": "Though man may read Simirtis and Shashtras and perform many rituals, yet without Thy vision, O Lord, there is no peace.",
              "additional_information": {}
            }
          },
          "Punjabi": {
            "Bhai Manmohan Singh": {
              "translation": "ਭਾਵੇਂ ਇਨਸਾਨ ਸਿਮ੍ਰਤੀਆਂ ਅਤੇ ਸ਼ਾਸਤਰ ਪੜ੍ਹ ਲਵੇ ਅਤੇ ਘਣੇਰੇ ਕਰਮ ਕਾਂਡ ਕਰੇ, ਪ੍ਰੰਤੂ ਤੇਰੇ ਦਰਸ਼ਨ ਬਗੈਰ ਹੇ ਸੁਆਮੀ! ਕੋਈ ਆਰਾਮ ਨਹੀਂ।",
              "additional_information": {}
            },
            "Fareedkot Teeka": {
              "translation": "ਹੇ ਰਾਮ ਜੀ! ਮੈਨੇ ਸਾਸਤ੍ਰ ਸਿੰਮ੍ਰਿਤਿਓਂ ਕੇ ਕਹੇ ਹੂਏ ਬਹੁਤ ਸੇ ਕਰਮ ਕੀਏ, ਪਰੰਤੂ ਤੁਮਾਰੇ ਦਰਸਨ ਬਿਨਾਂ ਸੁਖ ਨਹੀਂ ਪ੍ਰਾਪਤ ਹੂਆ॥੧॥",
              "additional_information": {
                "reference": ""
              }
            },
            "Prof. Sahib Singh": {
              "translation": "ਹੇ ਪਿਆਰੇ ਰਾਮ! ਅਨੇਕਾਂ ਲੋਕਾਂ ਨੇ ਸ਼ਾਸਤ੍ਰਾਂ ਸਿਮ੍ਰਿਤੀਆਂ ਦੇ ਲਿਖੇ ਅਨੁਸਾਰ (ਮਿਥੇ ਹੋਏ ਧਾਰਮਿਕ) ਕੰਮ ਕੀਤੇ, ਪਰ, ਹੇ ਪ੍ਰਭੂ! (ਇਹਨਾਂ ਕਰਮਾਂ ਨਾਲ ਤੇਰਾ ਦਰਸਨ ਨਸੀਬ ਨਾਹ ਹੋਇਆ, ਤੇ) ਤੇਰੇ ਦਰਸਨ ਤੋਂ ਬਿਨਾ ਆਤਮਕ ਆਨੰਦ ਨਹੀਂ ਮਿਲਦਾ ॥੧॥",
              "additional_information": {
                "arth": "ਪ੍ਰਭ = ਹੇ ਪ੍ਰਭੂ! ॥੧॥",
                "note": ""
              }
            }
          },
          "Spanish": {
            "SikhNet": {
              "translation": "Aunque los hombres lean los Smritis y los Shastras y realicen muchos rituales, sin Tu Visión, oh Señor, no hay Paz. (1)",
              "additional_information": {}
            }
          }
        }
      },
      {
        "id": "6HMM",
        "source_page": 408,
        "source_line": 3,
        "pronunciation": "",
        "pronunciation_information": "",
        "type": "Pankti",
        "gurmukhi": {
          "SGPC": "vrq nym, sMjm kir Qwky; nwnk. swD srin, pRB sMig vsY ]2]2]151]"
        },
        "translations": {
          "English": {
            "Dr. Sant Singh Khalsa": {
              "translation": "People have grown weary of observing fasts, vows and rigorous self-discipline; Nanak abides with God, in the Sanctuary of the Saints. ||2||2||151||",
              "additional_information": {}
            },
            "Bhai Manmohan Singh": {
              "translation": "Men have grown weary of observing fasts, vows and self mortification. In the sanctuary of saints Nanak abides with the Lord.",
              "additional_information": {}
            }
          },
          "Punjabi": {
            "Bhai Manmohan Singh": {
              "translation": "ਆਦਮੀ ਊਪਹਾਸ, ਪ੍ਰਣ ਤੇ ਸਵੈ-ਰੋਕ ਥਾਮ ਨਿਥਾਹੁੰਦੇ ਹੰਭ ਗਏ ਹਨ। ਸੰਤਾਂ ਦੀ ਸ਼ਰਣਾਗਤ ਅੰਦਰ ਨਾਨਕ ਸੁਆਮੀ ਦੇ ਨਾਲ ਵਸਦਾ ਹੈ।",
              "additional_information": {}
            },
            "Fareedkot Teeka": {
              "translation": "ਸ੍ਰੀ ਗੁਰੂ ਜੀ ਕਹਤੇ ਹੈਂ: ਸਭ ਪ੍ਰਕਾਰ ਕੇ ਬ੍ਰਤ ਨਿਜਮ ਸਰੀਰਕ ਸੰਜਮ ਭੀ ਕਰ ਕੇ ਥਕ ਗਏ, ਪਰੰਤੂ ਸੁਖ ਨਹੀਂ ਹੂਆ। ਆਪ ਕੇ ਸਾਧੋਂ ਕੀ ਸਰਣਿ ਲੈਣੇ ਕਰ, ਹੇ ਪ੍ਰਭੂ! ਤੇਰੇ ਸੰਗ ਬਸੇ, ਭਾਵ ਅਭੇਦ ਹੂਏ ਹਾਂ॥੨॥੨॥੧੫੧॥☬ਸਰਬ ਜੀਵੋਂ ਕੋ ਤਾੜਨਾ ਪੂਰਬਕ ਉਪਦੇਸ਼:",
              "additional_information": {
                "reference": ""
              }
            },
            "Prof. Sahib Singh": {
              "translation": "ਹੇ ਪ੍ਰਭੂ! (ਸ਼ਾਸਤ੍ਰਾਂ ਦੇ ਕਹੇ ਅਨੁਸਾਰ) ਅਨੇਕਾਂ ਲੋਕ ਵਰਤ ਰੱਖਦੇ ਰਹੇ, ਕਈ ਨੇਮ ਨਿਬਾਹੁੰਦੇ ਰਹੇ, ਇੰਦ੍ਰਿਆਂ ਨੂੰ ਵੱਸ ਕਰਨ ਦੇ ਜਤਨ ਕਰਦੇ ਰਹੇ, ਪਰ ਇਹ ਸਭ ਕੁਝ ਕਰ ਕੇ ਥੱਕ ਗਏ (ਤੇਰਾ ਦਰਸਨ ਪ੍ਰਾਪਤ ਨਾਹ ਹੋਇਆ)। ਹੇ ਨਾਨਕ! ਗੁਰੂ ਦੀ ਸਰਨ ਪਿਆਂ (ਮਨੁੱਖ ਦਾ ਮਨ) ਪਰਮਾਤਮਾ (ਦੇ ਚਰਨਾਂ) ਵਿਚ ਲੀਨ ਹੋ ਜਾਂਦਾ ਹੈ (ਤੇ ਮਨ ਨੂੰ ਸ਼ਾਂਤੀ ਪ੍ਰਾਪਤ ਹੋ ਜਾਂਦੀ ਹੈ) ॥੨॥੨॥੧੫੧॥",
              "additional_information": {
                "arth": "ਸੰਜਮ = ਇੰਦ੍ਰਿਆਂ ਨੂੰ ਕਾਬੂ ਕਰਨ ਦੇ ਸਾਧਨ। ਕਰਿ = ਕਰ ਕੇ। ਸਾਧ = ਗੁਰੂ। ਸੰਗਿ = ਨਾਲ ॥੨॥੨॥੧੫੧॥",
                "note": ""
              }
            }
          },
          "Spanish": {
            "SikhNet": {
              "translation": "Muchos se han agotado de hacer ayunos, votos y mandas. En el Santuario de los Santos, Nanak reside en el Señor. (2‑2‑151)",
              "additional_information": {}
            }
          }
        }
      }
    ]
  },
  {
    "id": "34V",
    "sttm_id": 1586,
    "writer": "Guru Arjan Dev Ji",
    "section": "Raag Aasaa",
    "subsection": null,
    "lines": [
      {
        "id": "DEFZ",
        "source_page": 408,
        "source_line": 5,
        "pronunciation": "",
        "pronunciation_information": "",
        "type": "Sirlekh",
        "gurmukhi": {
          "SGPC": "Awsw mhlw 5 Gru 15 pVqwl ]"
        },
        "translations": {
          "English": {
            "Dr. Sant Singh Khalsa": {
              "translation": "Aasaa, Fifth Mehl, Fifteenth House, Partaal:",
              "additional_information": {}
            },
            "Bhai Manmohan Singh": {
              "translation": "Asa 5th Guru.",
              "additional_information": {}
            }
          },
          "Punjabi": {
            "Bhai Manmohan Singh": {
              "translation": "ਆਸਾ ਪੰਜਵੀਂ ਪਾਤਸ਼ਾਹੀ।",
              "additional_information": {}
            },
            "Fareedkot Teeka": {
              "translation": "",
              "additional_information": {
                "reference": ""
              }
            },
            "Prof. Sahib Singh": {
              "translation": "ਰਾਗ ਆਸਾ, ਘਰ ੧੫ ਵਿੱਚ ਗੁਰੂ ਅਰਜਨਦੇਵ ਜੀ ਦੀ ਬਾਣੀ 'ਪੜਤਾਲ'।",
              "additional_information": {
                "arth": "ਪੜਤਾਲ = ਜਿਥੇ ਤਾਲ ਮੁੜ ਮੁੜ ਪਰਤਦਾ (-ਪੜ) ਰਹੇ, ਬਦਲਦਾ ਰਹੇ।",
                "note": ""
              }
            }
          },
          "Spanish": {
            "SikhNet": {
              "translation": "Asa, Mejl Guru Aryan, Quinto Canal Divino.",
              "additional_information": {}
            }
          }
        }
      },
      {
        "id": "YSS1",
        "source_page": 408,
        "source_line": 5,
        "pronunciation": "",
        "pronunciation_information": "",
        "type": "Manglacharan",
        "gurmukhi": {
          "SGPC": "<> siqgur pRswid ]"
        },
        "translations": {
          "English": {
            "Dr. Sant Singh Khalsa": {
              "translation": "One Universal Creator God. By The Grace Of The True Guru:",
              "additional_information": {}
            },
            "Bhai Manmohan Singh": {
              "translation": "There is but One God. By True Guru's grace He is attained.",
              "additional_information": {}
            }
          },
          "Punjabi": {
            "Bhai Manmohan Singh": {
              "translation": "ਵਾਹਿਗੁਰੂ ਕੇਵਲ ਇੱਕ ਹੈ। ਸੱਚੇ ਗੁਰਾਂ ਦੀ ਦਇਆ ਦੁਆਰਾ ਉਹ ਪਰਾਪਤ ਹੁੰਦਾ ਹੈ।",
              "additional_information": {}
            },
            "Fareedkot Teeka": {
              "translation": "",
              "additional_information": {
                "reference": ""
              }
            },
            "Prof. Sahib Singh": {
              "translation": "ਅਕਾਲ ਪੁਰਖ ਇੱਕ ਹੈ ਅਤੇ ਸਤਿਗੁਰੂ ਦੀ ਕਿਰਪਾ ਨਾਲ ਮਿਲਦਾ ਹੈ।",
              "additional_information": {
                "arth": "",
                "note": ""
              }
            }
          },
          "Spanish": {
            "SikhNet": {
              "translation": "Un Dios Creador del Universo, por la Gracia del Verdadero Guru",
              "additional_information": {}
            }
          }
        }
      },
      {
        "id": "RPKQ",
        "source_page": 408,
        "source_line": 6,
        "pronunciation": "",
        "pronunciation_information": "",
        "type": "Pankti",
        "gurmukhi": {
          "SGPC": "ibkwr mwieAw mwid soieE; sUJ bUJ. n AwvY ]"
        },
        "translations": {
          "English": {
            "Dr. Sant Singh Khalsa": {
              "translation": "He sleeps, intoxicated by corruption and Maya; he does not come to realize or understand.",
              "additional_information": {}
            },
            "Bhai Manmohan Singh": {
              "translation": "The man is sleep in the intoxication of sin and wealth and finds not understanding.",
              "additional_information": {}
            }
          },
          "Punjabi": {
            "Bhai Manmohan Singh": {
              "translation": "ਆਦਮੀ ਗੁਨਾਹ ਅਤੇ ਧਨ-ਦੌਲਤ ਦੇ ਨਸ਼ੇ ਅੰਦਰ ਸੁੱਤਾ ਪਿਆ ਹੈ ਅਤੇ ਸੋਚ-ਸਮਝ ਨਹੀਂ ਕਰਦਾ।",
              "additional_information": {}
            },
            "Fareedkot Teeka": {
              "translation": "ਬਿਕਾਰ ਜੋ ਹੈ ਕਾਮਾਦਿਕ ਔਰ ਮਾਇਆ ਇਨ ਕੇ (ਮਾਦਿ) ਮਦ ਮੇਂ ਜੀਵ ਸੋਇ ਰਹਾ ਹੈ, (ਸੂਝ) ਸਮਾਨ ਗ੍ਯਾਨ (ਬੂਝ) ਸਰੂਪ ਕੀ ਪਛਾਨ ਨਹੀਂ ਆਉਤੀ ਹੈ॥",
              "additional_information": {
                "reference": ""
              }
            },
            "Prof. Sahib Singh": {
              "translation": "ਵਿਕਾਰਾਂ ਵਿਚ ਮਾਇਆ ਦੇ ਨਸ਼ੇ ਵਿਚ ਮਨੁੱਖ ਸੁੱਤਾ ਰਹਿੰਦਾ ਹੈ, ਇਸ ਨੂੰ (ਸਹੀ ਜੀਵਨ-ਰਾਹ ਦੀ) ਅਕਲ ਨਹੀਂ ਆਉਂਦੀ।",
              "additional_information": {
                "arth": "ਮਾਦਿ = ਮਦਿ, ਨਸ਼ੇ ਵਿਚ। ਸੂਝ ਬੂਝ = (ਸਹੀ ਜੀਵਨ ਦੀ) ਅਕਲ।",
                "note": ""
              }
            }
          },
          "Spanish": {
            "SikhNet": {
              "translation": "Intoxicado por su propio ego, la riqueza y el vicio, el hombre duerme inconsciente de toda Sabiduría.",
              "additional_information": {}
            }
          }
        }
      },
      {
        "id": "EB7A",
        "source_page": 408,
        "source_line": 6,
        "pronunciation": "",
        "pronunciation_information": "",
        "type": "Pankti",
        "gurmukhi": {
          "SGPC": "pkir kys. jim auTwirE; qd hI Gir jwvY ]1]"
        },
        "translations": {
          "English": {
            "Dr. Sant Singh Khalsa": {
              "translation": "Seizing him by the hair, the Messenger of Death pulls him up; then, he comes to his senses. ||1||",
              "additional_information": {}
            },
            "Bhai Manmohan Singh": {
              "translation": "Seizing him by the hair, when death's courier lifts him up, then alone does he come to his senses.",
              "additional_information": {}
            }
          },
          "Punjabi": {
            "Bhai Manmohan Singh": {
              "translation": "ਵਾਲਾਂ ਤੋਂ ਪਕੜ ਕੇ ਜਦ ਮੌਤ ਦਾ ਦੂਤ ਉਸ ਨੂੰ ਉਛਾਲਦਾ ਹੈ, ਕੇਵਲ ਤਾਂ ਹੀ ਉਸ ਨੂੰ ਹੋਸ਼ ਆਉਂਦੀ ਹੈ।",
              "additional_information": {}
            },
            "Fareedkot Teeka": {
              "translation": "ਜਬ ਕੇਸੋਂ ਸੇ ਪਕੜ ਕਰ ਜਮ ਨੇ ਉਠਾਇਆ ਤਬ ਉਸ ਸਮ੍ਯ ਮੇਂ ਘਰ ਆਦਿ ਜਿਤਨੇ ਪਦਾਰਥ ਹੈਂ ਸਭ ਚਲੇ ਜਾਤੇ ਹੈਂ, ਕੋਈ ਸਹਾਇਕ ਨਹੀਂ ਬਨਤਾ ਹੈ। ਵਾਕ੍ਯਾ ਤਬ ਹੀ ਸਰੂਪ ਘਰ ਮੇਂ ਜਾਵੇਗਾ, ਕਿੰਤੂ ਨਹੀਂ ਜਾਵੇਗਾ। ਇਸ ਸੇ ਅਬ ਹੀ ਪੁਰੁਸਾਰਥੁ ਕਰ॥੧॥",
              "additional_information": {
                "reference": ""
              }
            },
            "Prof. Sahib Singh": {
              "translation": "(ਜਦੋਂ ਅੰਤ ਵੇਲੇ) ਜਮ ਨੇ ਇਸ ਨੂੰ ਕੇਸਾਂ ਤੋਂ ਫੜ ਕੇ ਉਠਾਇਆ (ਜਦੋਂ ਮੌਤ ਸਿਰ ਤੇ ਆ ਪਹੁੰਚੀ) ਤਦੋਂ ਹੀ ਇਸ ਨੂੰ ਹੋਸ਼ ਆਉਂਦੀ ਹੈ (ਕਿ ਸਾਰੀ ਉਮਰ ਕੁਰਾਹੇ ਪਿਆ ਰਿਹਾ) ॥੧॥",
              "additional_information": {
                "arth": "ਪਕਰਿ = ਫੜ ਕੇ। ਜਮਿ = ਜਮ ਨੇ। ਘਰਿ ਜਾਵੈ = ਆਪਣੇ ਘਰ ਵਿਚ ਜਾਂਦਾ ਹੈ, ਹੋਸ਼ ਵਿਚ ਆਉਂਦਾ ਹੈ (ਕਿ ਸਾਰੀ ਉਮਰ ਗ਼ਲਤੀ ਕਰਦਾ ਰਿਹਾ) ॥੧॥",
                "note": ""
              }
            }
          },
          "Spanish": {
            "SikhNet": {
              "translation": "Jalándolo por los cabellos, el mensajero de la muerte lo arrastra y lo levanta, sólo entonces se da cuenta. (1)",
              "additional_information": {}
            }
          }
        }
      },
      {
        "id": "3SJ6",
        "source_page": 408,
        "source_line": 7,
        "pronunciation": "",
        "pronunciation_information": "",
        "type": "Rahao",
        "gurmukhi": {
          "SGPC": "loB ibiKAw ibKY lwgy; ihir ivq, icq duKwhI ]"
        },
        "translations": {
          "English": {
            "Dr. Sant Singh Khalsa": {
              "translation": "Those who are attached to the poison of greed and sin grab at the wealth of others; they only bring pain on themselves.",
              "additional_information": {}
            },
            "Bhai Manmohan Singh": {
              "translation": "They, who are attached to the poison of avarice and evil passion, snatch others wealth and oppress their heart.",
              "additional_information": {}
            }
          },
          "Punjabi": {
            "Bhai Manmohan Singh": {
              "translation": "ਜੋ ਲਾਲਚ ਅਤੇ ਮੰਦ-ਵਿਸ਼ਿਆਂ ਦੀ ਜ਼ਹਿਰ ਨਾਲ ਚਿਮੜੇ ਹੋਏ ਹਨ, ਉਹ ਹੋਰਨਾ ਦੀ ਦੌਲਤ ਖੱਸਦੇ ਹਨ ਅਤੇ ਉਨ੍ਹਾਂ ਦੇ ਦਿਲਾਂ ਨੂੰ ਦੁੱਖੀ ਕਰਦੇ ਹਨ।",
              "additional_information": {}
            },
            "Fareedkot Teeka": {
              "translation": "ਜੀਵ ਬਿਖਿਓਂ ਕੇ ਲੋਭ ਮੇਂ ਲਗੇ ਹੂਏ ਔਰੋਂ ਕਾ (ਹਿਰਿ ਵਿਤ) ਧਨ ਹਰਿ ਕਰ ਕੇ ਉਨ ਕੇ ਚਿਤ ਕੋ ਦੁਖਾਉਤੇ ਹੈਂ॥",
              "additional_information": {
                "reference": ""
              }
            },
            "Prof. Sahib Singh": {
              "translation": "ਮਾਇਆ ਦੇ ਲੋਭ ਅਤੇ ਵਿਸ਼ਿਆਂ ਵਿਚ ਲੱਗੇ ਹੋਏ (ਪਰਾਇਆ) ਧਨ ਚੁਰਾ ਕੇ (ਦੂਜਿਆਂ ਦੇ) ਦਿਲ ਦੁਖਾਂਦੇ ਹਨ,",
              "additional_information": {
                "arth": "ਬਿਖਿਆ = ਮਾਇਆ। ਬਿਖੈ = ਵਿਸ਼ੇ। ਹਿਰਿ = ਚੁਰਾ ਕੇ। ਵਿਤ = ਧਨ। ਦੁਖਾਹੀ = ਦੁਖਾਹਿ, ਦੁਖਾਂਦੇ ਹਨ।",
                "note": ""
              }
            }
          },
          "Spanish": {
            "SikhNet": {
              "translation": "Está aferrado al veneno, a la avaricia y a las pasiones malignas, usurpa la riqueza de otros y oprime su corazón.",
              "additional_information": {}
            }
          }
        }
      },
      {
        "id": "MCVA",
        "source_page": 408,
        "source_line": 7,
        "pronunciation": "",
        "pronunciation_information": "",
        "type": "Rahao",
        "gurmukhi": {
          "SGPC": "iKn BMgunw kY. mwin mwqy; Asur. jwxih nwhI ]1] rhwau ]"
        },
        "translations": {
          "English": {
            "Dr. Sant Singh Khalsa": {
              "translation": "They are intoxicated by their pride in those things which shall be destroyed in an instant; those demons do not understand. ||1||Pause||",
              "additional_information": {}
            },
            "Bhai Manmohan Singh": {
              "translation": "These demons are intoxicated with the pride of what is destroyed in a moment and know not the Lord. Pause",
              "additional_information": {}
            }
          },
          "Punjabi": {
            "Bhai Manmohan Singh": {
              "translation": "ਭੂਤਨੇ ਇਕ ਮੁਹਤ ਵਿੱਚ ਨਾਸ ਹੋਣ ਵਾਲੀਆਂ ਚੀਜ਼ਾਂ ਦੇ ਹੰਕਾਰ ਵਿੱਚ ਮਤਵਾਲੇ ਹੋਏ ਹੋਏ ਹਨ ਅਤੇ ਪ੍ਰਭੂ ਨੂੰ ਨਹੀਂ ਜਾਣਦੇ। ਠਹਿਰਾਉ।",
              "additional_information": {}
            },
            "Fareedkot Teeka": {
              "translation": "ਜੋ ਪਦਾਰਥ ਖਿਨ ਮੇਂ ਨਾਸ ਹੋ ਜਾਨੇ ਵਾਲੇ ਹੈਂ ਤਿਨ ਕੇ ਮਾਨ ਮੇਂ ਮਸਤ ਹੂਏ ਹੂਏ (ਅਸੁਰੂ) ਆਸੁਰੀ ਸੰਪਤੀ ਵਾਲੇ 'ਪ੍ਰਮੇਸ੍ਵਰ' ਕੋ ਜਾਨਤੇ ਨਹੀਂ ਹੈਂ॥੧॥ ਰਹਾਉ ॥",
              "additional_information": {
                "reference": ""
              }
            },
            "Prof. Sahib Singh": {
              "translation": "ਪਲ ਵਿਚ ਸਾਥ ਛੱਡ ਜਾਣ ਵਾਲੀ ਮਾਇਆ ਦੇ ਮਾਣ ਵਿਚ ਮਸਤ ਨਿਰਦਈ ਮਨੁੱਖ ਸਮਝਦੇ ਨਹੀਂ (ਕਿ ਇਹ ਗ਼ਲਤ ਜੀਵਨ-ਰਾਹ ਹੈ) ॥੧॥ ਰਹਾਉ ॥",
              "additional_information": {
                "arth": "ਖਿਨ ਭੰਗੁਨ = ਖਿਨ-ਭੰਡਾਰ, ਖਿਨ ਵਿਚ ਨਾਸ ਹੋ ਜਾਣ ਵਾਲਾ। ਕੈ ਮਾਨਿ = ਦੇ ਮਾਣ ਵਿਚ। ਅਸੁਰ = ਦੈਂਤ, ਨਿਰਦਈ ਬੰਦੇ ॥੧॥ ਰਹਾਉ ॥",
                "note": ""
              }
            }
          },
          "Spanish": {
            "SikhNet": {
              "translation": "Sí, borracho con la arrogancia de las posesiones transitorias, anda como perro rabioso sin saber qué está haciendo. (1-Pausa)",
              "additional_information": {}
            }
          }
        }
      },
      {
        "id": "LP97",
        "source_page": 408,
        "source_line": 8,
        "pronunciation": "",
        "pronunciation_information": "",
        "type": "Pankti",
        "gurmukhi": {
          "SGPC": "byd swsqR jn pukwrih; sunY nwhI. forw ]"
        },
        "translations": {
          "English": {
            "Dr. Sant Singh Khalsa": {
              "translation": "The Vedas, the Shaastras and the holy men proclaim it, but the deaf do not hear it.",
              "additional_information": {}
            },
            "Bhai Manmohan Singh": {
              "translation": "The Vedas, the Shastras and the holy men cry out, but the deaf hears not.",
              "additional_information": {}
            }
          },
          "Punjabi": {
            "Bhai Manmohan Singh": {
              "translation": "ਵੇਦ, ਸ਼ਾਸਤ੍ਰ ਅਤੇ ਨੇਕ ਬੰਦੇ ਕੂਕਦੇ ਹਨ, ਪ੍ਰੰਤੂ ਬੋਲਾਂ ਸੁਣਦਾ ਹੀ ਨਹੀਂ।",
              "additional_information": {}
            },
            "Fareedkot Teeka": {
              "translation": "ਬੇਦ ਔਰ ਸਾਸਤ੍ਰ ਤਥਾ ਭਗਤਿ ਸਭ ਪੁਕਾਰ ਕੇ ਭਜਨ ਕੋ ਮੋਖ ਦਾਤਾ ਕਹਤੇ ਹੈਂ, ਪਰੰਤੂ ਐਸੇ (ਡੋਰਾ) ਬੋਲਾ ਹੂਆ ਹੈ ਸਰਧਾ ਬਿਚਾਰ ਕਾਨੋਂ ਸੇ ਰਹਿਤ ਕਿ ਕਿਸੀ ਕੀ ਨਹੀਂ ਸੁਨਤਾ ਹੈ॥",
              "additional_information": {
                "reference": ""
              }
            },
            "Prof. Sahib Singh": {
              "translation": "ਵੇਦ ਸ਼ਾਸਤ੍ਰ (ਆਦਿਕ ਧਰਮ-ਪੁਸਤਕ ਉਪਦੇਸ਼ ਕਰਦੇ ਹਨ) ਸੰਤ ਜਨ (ਭੀ) ਪੁਕਾਰ ਕੇ ਆਖਦੇ ਹਨ ਪਰ (ਮਾਇਆ ਦੇ ਨਸ਼ੇ ਦੇ ਕਾਰਨ) ਬੋਲਾ ਹੋ ਚੁਕਾ ਮਨੁੱਖ (ਉਹਨਾਂ ਦੇ ਉਪਦੇਸ਼ ਨੂੰ) ਸੁਣਦਾ ਨਹੀਂ।",
              "additional_information": {
                "arth": "ਪੁਕਾਰਹਿ = ਉੱਚੀ ਕੂਕ ਕੇ ਆਖਦੇ ਹਨ। ਡੋਰਾ = ਬੋਲਾ।",
                "note": ""
              }
            }
          },
          "Spanish": {
            "SikhNet": {
              "translation": "Los Vedas, los Shastras y los Hombres Santos proclaman el mensaje de la Conciencia Elevada, pero el sordo no escucha.",
              "additional_information": {}
            }
          }
        }
      },
      {
        "id": "P7XL",
        "source_page": 408,
        "source_line": 8,
        "pronunciation": "",
        "pronunciation_information": "",
        "type": "Pankti",
        "gurmukhi": {
          "SGPC": "inpit bwjI hwir. mUkw; pCuqwieE min Borw ]2]"
        },
        "translations": {
          "English": {
            "Dr. Sant Singh Khalsa": {
              "translation": "When the game of life is over, and he has lost, and he breathes his last, then the fool regrets and repents in his mind. ||2||",
              "additional_information": {}
            },
            "Bhai Manmohan Singh": {
              "translation": "The foolish man regrets in his mind, when the game of life is closed, and having lost it, he breathes his last.",
              "additional_information": {}
            }
          },
          "Punjabi": {
            "Bhai Manmohan Singh": {
              "translation": "ਜਦ ਜੀਵਨ ਖੇਡ ਖਤਮ ਹੋ ਜਾਂਦੀ ਹੈ, ਅਤੇ ਇਸ ਨੂੰ ਹਾਰਕੇ ਉਹ ਮਰ ਮੁੱਕ ਜਾਂਦਾ ਹੈ ਤਦ ਭੋਲਾ ਆਦਮੀ ਆਪਣੇ ਚਿੱਤ ਵਿੱਚ ਅਫਸੋਸ ਕਰਦਾ ਹੈ।",
              "additional_information": {}
            },
            "Fareedkot Teeka": {
              "translation": "(ਨਿਪਟਿ) ਅਤਸੈ ਕਰ ਕੇ ਜਬ ਮਾਨੁਖ ਦੇਹ ਰੂਪ ਬਾਜੀ ਕੋ (ਹਾਰਿ ਮੂਕਾ) ਹਾਰ ਚੁਕੇ ਤਬ ਭੋਲਾ ਜੀਵ ਪਸਚਾਤਾਪ ਕਰਤਾ ਭਯਾ॥੨॥☬ਜੇ ਕਹੈ ਮੈਨੇ ਯਗ ਆਦਕ ਕਰਮ ਕੀਏ ਹੈਂ ਤਿਨ ਕਾ ਫਲੁ ਮੇਰੇ ਕੋ ਮੋਖ ਪ੍ਰਾਪਤਿ ਹੋਵੇਗੀ? ਤਿਸ ਪਰ ਕਹਤੇ ਹੈਂ:",
              "additional_information": {
                "reference": ""
              }
            },
            "Prof. Sahib Singh": {
              "translation": "ਜਦੋਂ ਉੱਕਾ ਹੀ ਜੀਵਨ-ਬਾਜ਼ੀ ਹਾਰ ਕੇ ਅੰਤ ਸਮੇ ਤੇ ਆ ਪਹੁੰਚਦਾ ਹੈ ਤਦੋਂ ਇਹ ਮੂਰਖ ਆਪਣੇ ਮਨ ਵਿਚ ਪਛੁਤਾਂਦਾ ਹੈ ॥੨॥",
              "additional_information": {
                "arth": "ਨਿਪਟਿ = ਉੱਕਾ ਹੀ, ਬਿਲਕੁਲ। ਹਾਰਿ = ਹਾਰ ਕੇ। ਮੂਕਾ = ਅੰਤ ਸਮੇ ਤੇ ਆ ਪਹੁੰਚਦਾ ਹੈ। ਮਨਿ = ਮਨ ਵਿਚ। ਭੋਰਾ = ਮੂਰਖ ॥੨॥",
                "note": ""
              }
            }
          },
          "Spanish": {
            "SikhNet": {
              "translation": "El hombre tonto se arrepiente cuando el juego de la vida se acaba, y habiéndolo perdido, toma su último aliento. (2)",
              "additional_information": {}
            }
          }
        }
      },
      {
        "id": "CNU2",
        "source_page": 408,
        "source_line": 9,
        "pronunciation": "",
        "pronunciation_information": "",
        "type": "Pankti",
        "gurmukhi": {
          "SGPC": "fwnu sgl. gYr vjih BirAw; dIvwn lyKY. n pirAw ]"
        },
        "translations": {
          "English": {
            "Dr. Sant Singh Khalsa": {
              "translation": "He paid the fine, but it is in vain - in the Court of the Lord, his account is not credited.",
              "additional_information": {}
            },
            "Bhai Manmohan Singh": {
              "translation": "The entire fine he has paid without reasons and in God's court it is not credited.",
              "additional_information": {}
            }
          },
          "Punjabi": {
            "Bhai Manmohan Singh": {
              "translation": "ਸਾਰਾ ਜੁਰਮਾਨਾ ਉਸ ਨੇ ਬਗੈਰ ਸਬੱਬ ਦੇ ਹੀ ਤਾਰਿਆਂ ਹੈ। ਰੱਬ ਦੀ ਦਰਗਾਹ ਅੰਦਰ ਇਹ ਮੁਜਰੇ ਨਹੀਂ ਹੋਇਆ।",
              "additional_information": {}
            },
            "Fareedkot Teeka": {
              "translation": "ਜੋ ਸੰਤ ਜਨੋਂ ਸੇ (ਗੈਰ ਵਜਹਿ) ਵਿਰੁਧੁ, ਭਾਵ ਸਕਾਮ ਕਰਮ ਕੀਏ ਸੋ ਸਭ ਦੇਵਤੋਂ ਔ ਪਿਤ੍ਰ ਆਦਿਕੋਂ ਕਾ ਦੰਡ ਹੀ ਭਰਿਆ। ਸੋ ਕਰਮੋਂ ਕਾ ਸਮਦਾਉ ਪਰਮੇਸ੍ਵਰ ਕੇ ਦੀਵਾਨ ਮੇਂ ਲੇਖੈ ਨ ਪੜਾ, ਭਾਵ ਮੋਖ ਫਲ ਦਾਤਾ ਨਾ ਹੋਏ॥",
              "additional_information": {
                "reference": ""
              }
            },
            "Prof. Sahib Singh": {
              "translation": "(ਮਾਇਆ ਦੇ ਨਸ਼ੇ ਵਿਚ ਮਸਤ ਮਨੁੱਖ ਵਿਕਾਰਾਂ ਵਿਚ ਲੱਗਾ ਹੋਇਆ) ਵਿਅਰਥ ਹੀ ਡੰਨ ਭਰਦਾ ਰਹਿੰਦਾ ਹੈ (ਆਤਮਕ ਸਜ਼ਾ ਭੁਗਤਦਾ ਰਹਿੰਦਾ ਹੈ, ਅਜੇਹੇ ਕੰਮ ਹੀ ਕਰਦਾ ਹੈ ਜਿਨ੍ਹਾਂ ਦੇ ਕਾਰਨ) ਪਰਮਾਤਮਾ ਦੀ ਹਜ਼ੂਰੀ ਵਿਚ ਪਰਵਾਨ ਨਹੀਂ ਹੁੰਦਾ।",
              "additional_information": {
                "arth": "ਡਾਨੁ = ਡੰਨ। ਗੈਰ ਵਜਹਿ = ਅਕਾਰਨ, ਕਾਰਨ ਤੋਂ ਬਿਨਾ ਹੀ। ਦੀਵਾਨ ਲੇਖੈ = ਪਰਮਾਤਮਾ ਦੇ ਲੇਖੇ ਵਿਚ।",
                "note": ""
              }
            }
          },
          "Spanish": {
            "SikhNet": {
              "translation": "Todo su dolor fue en vano y no es admitido en la Corte de Dios.",
              "additional_information": {}
            }
          }
        }
      },
      {
        "id": "WE0Q",
        "source_page": 408,
        "source_line": 9,
        "pronunciation": "",
        "pronunciation_information": "",
        "type": "Pankti",
        "gurmukhi": {
          "SGPC": "jyNh kwrij. rhY El@w; soie. kwmu n kirAw ]3]"
        },
        "translations": {
          "English": {
            "Dr. Sant Singh Khalsa": {
              "translation": "Those deeds which would have covered him - those deeds, he has not done. ||3||",
              "additional_information": {}
            },
            "Bhai Manmohan Singh": {
              "translation": "The work which would have covered his sins that work he has not done.",
              "additional_information": {}
            }
          },
          "Punjabi": {
            "Bhai Manmohan Singh": {
              "translation": "ਕੰਮ, ਜਿਸ ਨਾਲ ਉਸ ਦੇ ਪਾਪ ਢੱਕੇ ਜਾਣੇ ਸਨ, ਉਹ ਕੰਮ ਉਸ ਨੇ ਨਹੀਂ ਕੀਤਾ।",
              "additional_information": {}
            },
            "Fareedkot Teeka": {
              "translation": "ਜਿਸ ਕਾਮ ਸੇ ਜੀਵ ਕਾ (ਓਲ੍ਹ੍ਹਾ) ਪੜਦਾ ਰਹਿ ਜਾਤਾ ਸੋ ਕਾਮੁ ਨਹੀਂ ਕੀਆ॥੩॥",
              "additional_information": {
                "reference": ""
              }
            },
            "Prof. Sahib Singh": {
              "translation": "ਜਿਸ ਕੰਮ ਦੇ ਕਰਨ ਨਾਲ ਪਰਮਾਤਮਾ ਦੇ ਦਰ ਤੇ ਇੱਜ਼ਤ ਬਣੇ ਉਹ ਕੰਮ ਇਹ ਕਦੇ ਭੀ ਨਹੀਂ ਕਰਦਾ ॥੩॥",
              "additional_information": {
                "arth": "ਜੇਂਹ ਕਾਰਜਿ = ਜਿਸ ਕੰਮ (ਦੇ ਕਰਨ) ਨਾਲ। ਓਲ੍ਹ੍ਹਾ = ਇੱਜ਼ਤ ॥੩॥",
                "note": ""
              }
            }
          },
          "Spanish": {
            "SikhNet": {
              "translation": "Aquélla práctica que pudo haber filtrado sus vicios, no la hizo. (3)",
              "additional_information": {}
            }
          }
        }
      },
      {
        "id": "ST2Q",
        "source_page": 408,
        "source_line": 10,
        "pronunciation": "",
        "pronunciation_information": "",
        "type": "Pankti",
        "gurmukhi": {
          "SGPC": "AYso jgu, moih guir idKwieE; qau eyk kIriq gwieAw ]"
        },
        "translations": {
          "English": {
            "Dr. Sant Singh Khalsa": {
              "translation": "The Guru has shown me the world to be thus; I sing the Kirtan of the Praises of the One Lord.",
              "additional_information": {}
            },
            "Bhai Manmohan Singh": {
              "translation": "When the Guru revealed to me the world to be such, then I began to sing the praises of the One Lord.",
              "additional_information": {}
            }
          },
          "Punjabi": {
            "Bhai Manmohan Singh": {
              "translation": "ਜਦ ਗੁਰਾਂ ਨੇ ਮੈਨੂੰ ਐਹੋ ਜੇਹਾ ਸੰਸਾਰ ਵਿਖਾਲ ਦਿੱਤਾ, ਤਦ ਮੈਂ ਇਕ ਸੁਆਮੀ ਦਾ ਜੱਸ ਗਾਇਨ ਕਰਨ ਲੱਗ ਪਿਆ।",
              "additional_information": {}
            },
            "Fareedkot Teeka": {
              "translation": "ਜਬ ਗੁਰੋਂ ਨੇ ਮੇਰੇ ਕੋ ਸੰਸਾਰੁ ਐਸਾ ਦਿਖਲਾਇ ਦੀਆ ਤਬ ਮੈਨੇ ਏਕ ਕੇ ਜਸ ਕੋ ਗਾਯਾ ਹੈ॥",
              "additional_information": {
                "reference": ""
              }
            },
            "Prof. Sahib Singh": {
              "translation": "ਜਦੋਂ ਗੁਰੂ ਨੇ ਮੈਨੂੰ ਇਹੋ ਜਿਹਾ (ਮਾਇਆ-ਗ੍ਰਸਿਆ) ਜਗਤ ਵਿਖਾ ਦਿੱਤਾ ਤਦੋਂ ਮੈਂ ਇਕ ਪਰਮਾਤਮਾ ਦੀ ਸਿਫ਼ਤ-ਸਾਲਾਹ ਕਰਨੀ ਸ਼ੁਰੂ ਕਰ ਦਿੱਤੀ,",
              "additional_information": {
                "arth": "ਮੋਹਿ = ਮੈਨੂੰ। ਗੁਰਿ = ਗੁਰੂ ਨੇ। ਤਉ = ਤਦੋਂ। ਏਕ = ਇਕ (ਪਰਮਾਤਮਾ) ਦੀ। ਕੀਰਤਿ = ਸਿਫ਼ਤ-ਸਾਲਾਹ।",
                "note": ""
              }
            }
          },
          "Spanish": {
            "SikhNet": {
              "translation": "Cuando el Guru me reveló el mundo de esta forma, entonces empecé a cantar las Alabanzas del Único Señor.",
              "additional_information": {}
            }
          }
        }
      },
      {
        "id": "W6Q4",
        "source_page": 408,
        "source_line": 10,
        "pronunciation": "",
        "pronunciation_information": "",
        "type": "Pankti",
        "gurmukhi": {
          "SGPC": "mwnu qwnu qij isAwnp; srix nwnku AwieAw ]4]1]152]"
        },
        "translations": {
          "English": {
            "Dr. Sant Singh Khalsa": {
              "translation": "Renouncing his pride in strength and cleverness, Nanak has come to the Lord's Sanctuary. ||4||1||152||",
              "additional_information": {}
            },
            "Bhai Manmohan Singh": {
              "translation": "Having renounced pride in his strength, Nanak has entered Lord's sanctuary.",
              "additional_information": {}
            }
          },
          "Punjabi": {
            "Bhai Manmohan Singh": {
              "translation": "ਆਪਣੇ ਬਲ ਅਤੇ ਦਾਨਾਈ ਦਾ ਹੰਕਾਰ ਛੱਡ ਕੇ ਨਾਨਕ ਨੇ ਸੁਆਮੀ ਦੀ ਸ਼ਰਣਾਗਤਿ ਸੰਭਾਲੀ ਹੈ।",
              "additional_information": {}
            },
            "Fareedkot Teeka": {
              "translation": "ਸ੍ਰੀ ਗੁਰੂ ਜੀ ਕਹਤੇ ਹੈਂ: ਮਾਨ ਔਰ ਤਾਣ ਬਲ ਬੁਧੀ ਕੀ ਸਿਆਨਪ ਸਭ ਤਿਆਗ ਕਰ ਮੈਂ ਸਤਗੁਰੋਂ ਕੀ ਸ਼ਰਣ ਮੇਂ ਪ੍ਰਾਪਤ ਭ੍ਯਾ ਹੂੰ॥੪॥੧॥੧੫੨॥☬ਜੇ ਕਹੈ ਗੁਰੋਂ ਕੀ ਸਰਣ ਆਇ ਕਰ ਤੁਮ ਨੇ ਕਿਆ ਕੀਆ? ਸੋ ਕਹਤੇ ਹੈਂ:",
              "additional_information": {
                "reference": ""
              }
            },
            "Prof. Sahib Singh": {
              "translation": "ਤਦੋਂ ਮਾਣ ਤਿਆਗ ਕੇ (ਹੋਰ) ਆਸਰਾ ਛੱਡ ਕੇ, ਚੁਤਰਾਈਆਂ ਤਜ ਕੇ (ਮੈਂ ਦਾਸ) ਨਾਨਕ ਪਰਮਾਤਮਾ ਦੀ ਸਰਨ ਆ ਪਿਆ ॥੪॥੧॥੧੫੨॥",
              "additional_information": {
                "arth": "ਤਜਿ = ਛੱਡ ਕੇ ॥੪॥੧॥੧੫੨॥",
                "note": "* ਨੋਟ: ਇਥੋਂ ਘਰੁ ੧੫ ਦੇ ਸ਼ਬਦ ਸ਼ੁਰੂ ਹੁੰਦੇ ਹਨ।"
              }
            }
          },
          "Spanish": {
            "SikhNet": {
              "translation": "Habiendo renunciado al orgullo, al poder y a la astucia, Nanak ha entrado en el Refugio del Señor. (4‑1‑152)",
              "additional_information": {}
            }
          }
        }
      }
    ]
  },
  {
    "id": "T0J",
    "sttm_id": 1587,
    "writer": "Guru Arjan Dev Ji",
    "section": "Raag Aasaa",
    "subsection": null,
    "lines": [
      {
        "id": "XVW3",
        "source_page": 408,
        "source_line": 11,
        "pronunciation": "",
        "pronunciation_information": "",
        "type": "Sirlekh",
        "gurmukhi": {
          "SGPC": "Awsw mhlw 5 ]"
        },
        "translations": {
          "English": {
            "Dr. Sant Singh Khalsa": {
              "translation": "Aasaa, Fifth Mehl:",
              "additional_information": {}
            },
            "Bhai Manmohan Singh": {
              "translation": "Asa 5th Guru.",
              "additional_information": {}
            }
          },
          "Punjabi": {
            "Bhai Manmohan Singh": {
              "translation": "ਆਸਾ ਪੰਜਵੀਂ ਪਾਤਸ਼ਾਹੀ।",
              "additional_information": {}
            },
            "Fareedkot Teeka": {
              "translation": "",
              "additional_information": {
                "reference": ""
              }
            },
            "Prof. Sahib Singh": {
              "translation": "ਰਾਗ ਆਸਾ ਵਿੱਚ ਗੁਰੂ ਅਰਜਨਦੇਵ ਜੀ ਦੀ ਬਾਣੀ।",
              "additional_information": {
                "arth": "",
                "note": ""
              }
            }
          },
          "Spanish": {
            "SikhNet": {
              "translation": "Asa, Mejl Guru Aryan, Quinto Canal Divino.",
              "additional_information": {}
            }
          }
        }
      },
      {
        "id": "LMU5",
        "source_page": 408,
        "source_line": 11,
        "pronunciation": "",
        "pronunciation_information": "",
        "type": "Rahao",
        "gurmukhi": {
          "SGPC": "bwpwir. goivMd nwey ]"
        },
        "translations": {
          "English": {
            "Dr. Sant Singh Khalsa": {
              "translation": "Dealing in the Name of the Lord of the Universe,",
              "additional_information": {}
            },
            "Bhai Manmohan Singh": {
              "translation": "By dealing in the Lord's, Name,",
              "additional_information": {}
            }
          },
          "Punjabi": {
            "Bhai Manmohan Singh": {
              "translation": "ਸੁਆਮੀ ਦੇ ਨਾਮ ਦੇ ਵਣਜ ਦੁਆਰਾ,",
              "additional_information": {}
            },
            "Fareedkot Teeka": {
              "translation": "ਹਮਨੇ ਗੋਬਿੰਦ ਕੇ ਨਾਮ ਕਾ ਬਾਪਾਰ ਕੀਆ ਹੈ॥",
              "additional_information": {
                "reference": ""
              }
            },
            "Prof. Sahib Singh": {
              "translation": "ਜੇਹੜਾ ਮਨੁੱਖ ਪਰਮਾਤਮਾ ਦੇ ਨਾਮ ਦੇ ਵਪਾਰ ਵਿਚ ਲੱਗ ਪੈਂਦਾ ਹੈ,",
              "additional_information": {
                "arth": "ਬਾਪਾਰਿ = ਵਪਾਰ ਵਿਚ, ਵਣਜ ਦੀ ਰਾਹੀਂ। ਨਾਏ = ਪਰਮਾਤਮਾ ਦੇ ਨਾਮ ਦੇ।",
                "note": ""
              }
            }
          },
          "Spanish": {
            "SikhNet": {
              "translation": "Tratando con el Naam, el Nombre del Señor,",
              "additional_information": {}
            }
          }
        }
      },
      {
        "id": "1P7Z",
        "source_page": 408,
        "source_line": 11,
        "pronunciation": "",
        "pronunciation_information": "",
        "type": "Rahao",
        "gurmukhi": {
          "SGPC": "swD sMq mnwey, ipRA pwey gun gwey; pMc nwd, qUr bjwey ]1] rhwau ]"
        },
        "translations": {
          "English": {
            "Dr. Sant Singh Khalsa": {
              "translation": "and pleasing the Saints and holy men, obtain the Beloved Lord and sing His Glorious Praises; play the sound current of the Naad with the five instruments. ||1||Pause||",
              "additional_information": {}
            },
            "Bhai Manmohan Singh": {
              "translation": "please the saints and pious persons, obtain the Beloved sing His praises and play the melody with five musical instruments. Pause.",
              "additional_information": {}
            }
          },
          "Punjabi": {
            "Bhai Manmohan Singh": {
              "translation": "ਜਗਿਆਸੂ ਅਤੇ ਪਵਿੱਤਰ ਪੁਰਸ਼ ਪ੍ਰਸੰਨ ਕਰ, ਪ੍ਰੀਤਮ ਪਾ ਕੇ ਉਸ ਦੀਆਂ ਸਿਫਤਾਂ ਗਾਇਨ ਕਰ ਅਤੇ ਪੰਜ ਸੰਗਤੀਤਕ ਸਾਜ਼ ਵਜਾ ਤੇ ਕੀਰਤਨ ਦੀਆਂ ਧੂਨੀਆਂ ਸੁਣ। ਠਹਿਰਾਉ।",
              "additional_information": {}
            },
            "Fareedkot Teeka": {
              "translation": "ਸਾਧੂ ਜੋ ਹੈਂ (ਸੰਤ) ਸਾਂਤ ਰੂਪ ਸੋ ਮਨਾਏ ਹੈਂ ਔਰ ਜਬ ਹਰੀ ਕੇ ਗੁਣ ਗਾਏ ਹੈਂ ਤਬ (ਪ੍ਰਿਅ) ਪਤੀ ਹਰੀ ਪਾਏ ਹੈਂ। (ਪੰਚ) ਸੰਤੋਂ ਕੇ (ਨਾਦ) ਸਬਦ ਰੂਪ (ਤੂਰ) ਬਾਜੇ ਹੈਂ ਅਰਥਾਤ ਗੁਰ ਉਪਦੇਸ਼ ਕੋ ਪ੍ਰਗਟ ਕੀਆ ਹੈ॥੧॥ ਰਹਾਉ ॥",
              "additional_information": {
                "reference": ""
              }
            },
            "Prof. Sahib Singh": {
              "translation": "ਪਰਮਾਤਮਾ ਦੇ ਗੁਣ ਗਾਂਦਾ ਹੈ ਸੰਤ ਜਨਾਂ ਦੀ ਪ੍ਰਸੰਨਤਾ ਹਾਸਲ ਕਰ ਲੈਂਦਾ ਹੈ, ਉਸ ਨੂੰ ਪਿਆਰੇ ਪ੍ਰਭੂ ਦਾ ਮਿਲਾਪ ਪ੍ਰਾਪਤ ਹੋ ਜਾਂਦਾ ਹੈ ਉਸ ਦੇ ਅੰਦਰ, ਮਾਨੋ, ਪੰਜ ਕਿਸਮਾਂ ਦੇ ਸਾਜ ਵੱਜਣ ਲੱਗ ਪੈਂਦੇ ਹਨ ॥੧॥ ਰਹਾਉ ॥",
              "additional_information": {
                "arth": "ਮਨਾਏ = ਪ੍ਰਸੰਨ ਕੀਤੇ। ਪ੍ਰਿਅ ਪਾਏ = ਪਿਆਰੇ (ਦਾ ਦਰਸਨ) ਪਾਇਆ। ਪੰਚ ਨਾਦ ਤੂਰ = ਪੰਜ ਕਿਸਮਾਂ ਦੀਆਂ ਆਵਾਜ਼ਾਂ ਦੇਣ ਵਾਲੇ ਵਾਜੇ {ਤੰਤੀ ਸਾਜ, ਧਾਤ ਦੇ, ਫੂਕ ਨਾਲ ਵਜਾਏ ਜਾਣ ਵਾਲੇ, ਤਬਲਾ ਆਦਿਕ, ਘੜਾ ਆਦਿਕ} ॥੧॥ ਰਹਾਉ ॥",
                "note": ""
              }
            }
          },
          "Spanish": {
            "SikhNet": {
              "translation": "los Santos y las personas piadosas están complacidos, y el Bienamado es obtenido. Sus Alabanzas son cantadas, y la Melodía de los cinco instrumentos musicales resuena. (1‑Pausa)",
              "additional_information": {}
            }
          }
        }
      },
      {
        "id": "R19C",
        "source_page": 408,
        "source_line": 12,
        "pronunciation": "",
        "pronunciation_information": "",
        "type": "Pankti",
        "gurmukhi": {
          "SGPC": "ikrpw pwey, shjwey drswey; Ab rwiqAw goivMd isau ]"
        },
        "translations": {
          "English": {
            "Dr. Sant Singh Khalsa": {
              "translation": "Obtaining His Mercy, I easily gained the Blessed Vision of His Darshan; now, I am imbued with the Love of the Lord of the Universe.",
              "additional_information": {}
            },
            "Bhai Manmohan Singh": {
              "translation": "When I obtained Lord's favour, I, easily, has a vision of Him and now, I am imbued with Lord's love.",
              "additional_information": {}
            }
          },
          "Punjabi": {
            "Bhai Manmohan Singh": {
              "translation": "ਜਦ ਮੈਂ ਸੁਆਮੀ ਦੀ ਦਇਆ ਦਾ ਪਾਤ੍ਰ ਹੋਇਆ, ਮੈਂ ਸੁਖੈਨ ਹੀ ਉਸ ਦਾ ਦਰਸ਼ਨ ਪਾ ਲਿਆ ਅਤੇ ਹੁਣ ਮੈਂ ਪ੍ਰਭੂ ਦੀ ਪ੍ਰੀਤ ਨਾਲ ਰੰਗਿਆ ਹੋਇਆ ਹਾਂ।",
              "additional_information": {}
            },
            "Fareedkot Teeka": {
              "translation": "ਪਰਮੇਸ੍ਵਰ ਕੀ ਕ੍ਰਿਪਾ ਸੇ ਹਮ ਨੇ ਯਹ ਗੁਣ ਪਾਏ ਹੈਂ ਅਰ ਹਮਾਰੇ ਅੰਤਸਕਰਣ (ਸਹਜਾਏ) ਸਾਂਤ ਕੋ ਪ੍ਰਾਪਤ ਹੂਏ ਹੈਂ। ਜਿਸ ਕ੍ਰਿਪਾ ਨੇ ਹਮ ਕੋ ਅਕਾਲ ਪੁਰਖ (ਦਰਸਾਏ) ਦਿਖਲਾਏ ਹੈਂ ਅਬ ਹਮ ਤਿਸ ਗੋਬਿੰਦ ਕੇ ਸਾਥ ਰਾਤੇ ਹੈਂ॥",
              "additional_information": {
                "reference": ""
              }
            },
            "Prof. Sahib Singh": {
              "translation": "ਪਰਮਾਤਮਾ ਦੀ ਕਿਰਪਾ ਨਾਲ ਜਿਸ ਮਨੁੱਖ ਨੂੰ ਆਤਮਕ ਅਡੋਲਤਾ ਪ੍ਰਾਪਤ ਹੋ ਜਾਂਦੀ ਹੈ, ਪਰਮਾਤਮਾ ਦਾ ਦਰਸਨ ਹੋ ਜਾਂਦਾ ਹੈ ਉਹ ਸਦਾ ਲਈ ਪਰਮਾਤਮਾ ਦੇ ਪਿਆਰ-ਰੰਗ ਵਿਚ ਰੰਗਿਆ ਜਾਂਦਾ ਹੈ।",
              "additional_information": {
                "arth": "ਸਹਜਾਏ = ਸਹਜ ਅਵਸਥਾ, ਆਤਮਕ ਅਡੋਲਤਾ। ਰਾਤਿਆ = ਰੰਗੇ ਗਏ। ਸਿਉ = ਨਾਲ।",
                "note": ""
              }
            }
          },
          "Spanish": {
            "SikhNet": {
              "translation": "Cuando obtuve el Favor del Señor, obtuve fácilmente la Visión de Él, y ahora estoy imbuido en el Amor del Señor.",
              "additional_information": {}
            }
          }
        }
      },
      {
        "id": "KXMF",
        "source_page": 408,
        "source_line": 13,
        "pronunciation": "",
        "pronunciation_information": "",
        "type": "Pankti",
        "gurmukhi": {
          "SGPC": "sMq syiv, pRIiq nwQ; rMgu lwln lwey ]1]"
        },
        "translations": {
          "English": {
            "Dr. Sant Singh Khalsa": {
              "translation": "Serving the Saints, I feel love and affection for my Beloved Lord Master. ||1||",
              "additional_information": {}
            },
            "Bhai Manmohan Singh": {
              "translation": "By serving the saints, I imbibed love and affection for my Beloved Master.",
              "additional_information": {}
            }
          },
          "Punjabi": {
            "Bhai Manmohan Singh": {
              "translation": "ਸਾਧੂਆਂ ਦੀ ਟਹਿਲ ਕਮਾਉਣ ਦੁਆਰਾ ਮੇਰੀ ਪਿਰਹੜੀ ਅਤੇ ਮੁਹੱਬਤ ਪ੍ਰੀਤਮ ਮਾਲਕ ਨਾਲ ਪੈ ਗਈ ਹੈ।",
              "additional_information": {}
            },
            "Fareedkot Teeka": {
              "translation": "ਸੰਤੋਂ ਕੀ ਸੇਵਾ ਕਰ ਸ੍ਵਾਮੀ ਕੇ ਸਾਥ ਪ੍ਰੀਤੀ ਹੋਈ ਹੈ ਅਬ ਤਿਸੀ (ਲਾਲਨ) ਪਿਆਰੇ ਕੇ ਸਾਥ ਪ੍ਰੇਮ ਲਗਾ ਰਹੇ ਹੈਂ॥੧॥",
              "additional_information": {
                "reference": ""
              }
            },
            "Prof. Sahib Singh": {
              "translation": "ਗੁਰੂ ਦੀ ਦੱਸੀ ਸੇਵਾ ਦੀ ਬਰਕਤਿ ਨਾਲ ਉਸ ਨੂੰ ਖਸਮ-ਪ੍ਰਭੂ ਦੀ ਪ੍ਰੀਤ ਪ੍ਰਾਪਤ ਹੋ ਜਾਂਦੀ ਹੈ; ਲਾਲ ਪਿਆਰੇ ਦਾ ਪਿਆਰ-ਰੰਗ ਚੜ੍ਹ ਜਾਂਦਾ ਹੈ ॥੧॥",
              "additional_information": {
                "arth": "ਸੇਵਿ = ਸੇਵਾ ਕਰ ਕੇ। ਰੰਗੁ ਲਾਲਨ = ਪਿਆਰੇ ਪ੍ਰਭੂ ਦਾ ਪ੍ਰੇਮ ॥੧॥",
                "note": ""
              }
            }
          },
          "Spanish": {
            "SikhNet": {
              "translation": "Sirviendo a los Santos, tomo Amor y Afecto por mi Querido Maestro. (1)",
              "additional_information": {}
            }
          }
        }
      },
      {
        "id": "FZZM",
        "source_page": 408,
        "source_line": 13,
        "pronunciation": "",
        "pronunciation_information": "",
        "type": "Pankti",
        "gurmukhi": {
          "SGPC": "gur igAwnu min idRVwey rhswey, nhI Awey; shjwey. min inDwnu pwey ]"
        },
        "translations": {
          "English": {
            "Dr. Sant Singh Khalsa": {
              "translation": "The Guru has implanted spiritual wisdom within my mind, and I rejoice that I shall not have to come back again. I have obtained celestial poise, and the treasure within my mind.",
              "additional_information": {}
            },
            "Bhai Manmohan Singh": {
              "translation": "The Guru has fixed Divine Knowledge in my mind, and I am rejoiced that I shall not come (born) again, I have attained equipoise and God's treasure within my heart.",
              "additional_information": {}
            }
          },
          "Punjabi": {
            "Bhai Manmohan Singh": {
              "translation": "ਗੁਰਾਂ ਨੇ ਬ੍ਰਹਿਮ-ਬੋਧ ਮੇਰੇ ਹਿਰਦੇ ਅੰਦਰ ਪੱਕਾ ਕਰ ਦਿੱਤਾ ਹੈ ਅਤੇ ਮੈਂ ਖੁਸ਼ ਹਾਂ ਕਿ ਮੈਂ ਮੁੜ ਕੇ ਨਹੀਂ ਆਵਾਂਗਾ, ਮੇਰੇ ਦਿਲ ਅੰਦਰ ਮੈਨੂੰ ਅਡੋਲਤਾ ਅਤੇ ਰੱਬੀ ਖ਼ਜ਼ਾਨਾ ਪਰਾਪਤ ਹੋ ਗਏ ਹਨ।",
              "additional_information": {}
            },
            "Fareedkot Teeka": {
              "translation": "ਜਬ ਗੁਰੋਂ ਨੇ ਮਨ ਮੇਂ ਗਿਆਨ ਅਰ ਧਿਆਨ ਦ੍ਰਿੜ ਕਰਾਇ ਦੀਏ ਤਬ ਹਮ ਆਨੰਦ ਮੇਂ ਆਏ ਫੇਰ ਹਮਾਰੇ ਅੰਤਸ਼ਕਰਣ ਆਨ ਬਿਖਿਓਂ ਕੀ ਓਰ ਨਹੀਂ ਆਏ। ਸੋ ਅੰਤਹਕਰਣ ਸ਼ਾਂਤੀ ਮੇਂ ਆਏ ਹੈਂ, ਭਾਵ ਅਬ ਔਰ ਕਾ ਬਚਨ ਕੁਬਚਨ ਭੀ ਸਹਾਰ ਲੇਤੇ ਹੈਂ। ਅਬ ਮਨ ਹੀ ਮੇਂ ਸਰਬ ਕਾ ਆਸਰਾ ਰੂਪ ਹਰੀ ਜੀ ਪਾਏ ਹੈਂ॥",
              "additional_information": {
                "reference": ""
              }
            },
            "Prof. Sahib Singh": {
              "translation": "ਜੇਹੜਾ ਮਨੁੱਖ ਆਪਣੇ ਮਨ ਵਿਚ ਗੁਰੂ ਦੇ ਦਿੱਤੇ ਗਿਆਨ ਨੂੰ ਪੱਕਾ ਕਰ ਲੈਂਦਾ ਹੈ, ਉਸ ਦੇ ਅੰਦਰ ਖਿੜਾਉ ਪੈਦਾ ਹੋ ਜਾਂਦਾ ਹੈ ਉਹ ਜਨਮ ਮਰਨ ਦੇ ਗੇੜ ਵਿਚ ਨਹੀਂ ਪੈਂਦਾ, ਉਸ ਦੇ ਅੰਦਰ ਆਤਮਕ ਅਡੋਲਤਾ ਪੈਦਾ ਹੋ ਜਾਂਦੀ ਹੈ, ਉਹ ਆਪਣੇ ਮਨ ਵਿਚ ਨਾਮ-ਖ਼ਜ਼ਾਨਾ ਲੱਭ ਲੈਂਦਾ ਹੈ।",
              "additional_information": {
                "arth": "ਮਨਿ = ਮਨ ਵਿਚ। ਰਹਸਾਏ = ਰਹਸ, ਖਿੜਾਉ। ਨਹੀ ਆਏ = ਜਨਮ ਮਰਨ ਦੇ ਗੇੜ ਵਿਚ ਨਹੀਂ ਪਏ। ਨਿਧਾਨੁ = ਖ਼ਜ਼ਾਨਾ।",
                "note": ""
              }
            }
          },
          "Spanish": {
            "SikhNet": {
              "translation": "El Guru ha instalado el Conocimiento Divino en mi mente, y estoy feliz de no tener que regresar de nuevo. He obtenido la Calma, y el Tesoro de Dios vive dentro de mi corazón.",
              "additional_information": {}
            }
          }
        }
      },
      {
        "id": "0D96",
        "source_page": 408,
        "source_line": 14,
        "pronunciation": "",
        "pronunciation_information": "",
        "type": "Pankti",
        "gurmukhi": {
          "SGPC": "sB qjI; mnY kI kwm krw ]"
        },
        "translations": {
          "English": {
            "Dr. Sant Singh Khalsa": {
              "translation": "I have renounced all of the affairs of my mind's desires.",
              "additional_information": {}
            },
            "Bhai Manmohan Singh": {
              "translation": "I have renounced all the affairs of my mind's desire.",
              "additional_information": {}
            }
          },
          "Punjabi": {
            "Bhai Manmohan Singh": {
              "translation": "ਮੈਂ ਆਪਣੇ ਚਿੱਤ ਦੀ ਖਾਹਿਸ਼ ਦੇ ਸਾਰੇ ਕੰਮ ਛੱਡ ਛੱਡੇ ਹਨ।",
              "additional_information": {}
            },
            "Fareedkot Teeka": {
              "translation": "ਔਰ ਮਨ ਕੀ ਜੋ ਕਾਮ ਕਲਾ ਵਾ ਕਲਪਨਾ ਥੀ ਸੋ ਸਭ ਤਜੀ ਹੈ॥",
              "additional_information": {
                "reference": ""
              }
            },
            "Prof. Sahib Singh": {
              "translation": "ਉਹ ਆਪਣੇ ਮਨ ਦੀਆਂ ਸਾਰੀਆਂ ਵਾਸ਼ਨਾਂ ਤਿਆਗ ਦੇਂਦਾ ਹੈ।",
              "additional_information": {
                "arth": "ਮਨੈ ਕੀ = ਮਨ ਦੀ। ਕਾਮ ਕਰਾ = ਵਾਸ਼ਨਾ।",
                "note": ""
              }
            }
          },
          "Spanish": {
            "SikhNet": {
              "translation": "He renunciado y parado todos los deseos de mi mente,",
              "additional_information": {}
            }
          }
        }
      },
      {
        "id": "1XPH",
        "source_page": 408,
        "source_line": 14,
        "pronunciation": "",
        "pronunciation_information": "",
        "type": "Pankti",
        "gurmukhi": {
          "SGPC": "icru icru icru icru BieAw; min bhuqu ipAws lwgI ]"
        },
        "translations": {
          "English": {
            "Dr. Sant Singh Khalsa": {
              "translation": "It has been so long, so long, so long, so very long, since my mind has felt such a great thirst.",
              "additional_information": {}
            },
            "Bhai Manmohan Singh": {
              "translation": "It is long, long and long since my soul has felt a great thirst (for God's vision).",
              "additional_information": {}
            }
          },
          "Punjabi": {
            "Bhai Manmohan Singh": {
              "translation": "ਦੇਰ, ਦੇਰ, ਦੇਰ, ਦੇਰ, ਹੋ ਗਈ ਹੈ ਜਦ ਤੋਂ ਮੇਰੀ ਆਤਮਾ ਨੂੰ (ਦਰਸ਼ਨਾਂ ਦੀ) ਘਣੀ ਤੇਹ ਲੱਗੀ ਹੋਈ ਹੈ।",
              "additional_information": {}
            },
            "Fareedkot Teeka": {
              "translation": "(ਚਿਰੁ ਚਿਰੁ ਚਿਰੁ ਚਿਰੁ) ਚਾਰੋਂ ਜੁਗੋਂ ਕੀ ਚੌਂਕੜੀਆਂ ਬੀਤ ਗਈ ਹੈਂ, ਇਸ ਸੇ ਮਨ ਕੋ ਬੜੀ ਪਿਆਸ ਲਗ ਰਹੀ॥☬ਜੇ ਕਹੈ ਆਪ ਕੋ ਪੂਰਬੋਕਤ ਗੁਣ ਕਿਸ ਪ੍ਰਕਾਰ ਪ੍ਰਾਪਤ ਹੂਏ ਹੈਂ? ਸੋ ਕਹਤੇ ਹੈਂ: ਐਸੇ ਬੇਨਤੀ ਕਰੀ ਹੈ, ਸੋ ਦਿਖਾਵਤੇ ਹੈਂ:",
              "additional_information": {
                "reference": ""
              }
            },
            "Prof. Sahib Singh": {
              "translation": "(ਤੇਰਾ ਦਰਸਨ ਕੀਤਿਆਂ ਮੈਨੂੰ) ਬਹੁਤ ਚਿਰ ਹੋ ਚੁਕਾ ਹੈ, ਮੇਰੇ ਮਨ ਵਿਚ ਤੇਰੇ ਦਰਸਨ ਦੀ ਤਾਂਘ ਪੈਦਾ ਹੋ ਰਹੀ ਹੈ,",
              "additional_information": {
                "arth": "",
                "note": ""
              }
            }
          },
          "Spanish": {
            "SikhNet": {
              "translation": "hace ya mucho, mucho, mucho, desde que mi Alma sintió sed.",
              "additional_information": {}
            }
          }
        }
      },
      {
        "id": "4D56",
        "source_page": 408,
        "source_line": 15,
        "pronunciation": "",
        "pronunciation_information": "",
        "type": "Pankti",
        "gurmukhi": {
          "SGPC": "hir drsno idKwvhu. moih qum bqwvhu ]"
        },
        "translations": {
          "English": {
            "Dr. Sant Singh Khalsa": {
              "translation": "Please, reveal to me the Blessed Vision of Your Darshan, and show Yourself to me.",
              "additional_information": {}
            },
            "Bhai Manmohan Singh": {
              "translation": "O God, show me Thine sight and apprise me of Thy presence.",
              "additional_information": {}
            }
          },
          "Punjabi": {
            "Bhai Manmohan Singh": {
              "translation": "ਹੇ ਵਾਹਿਗੁਰੂ! ਮੈਨੂੰ ਆਪ ਦਾ ਦੀਦਾਰ ਵਿਖਾਲ, ਅਤੇ ਮੈਂ ਕੀ ਆਪਣੀ ਹਜ਼ੂਰੀ ਦਰਸਾ।",
              "additional_information": {}
            },
            "Fareedkot Teeka": {
              "translation": "ਸਭ ਸੰਤੋਂ ਸੇ ਯਹੀ ਬੇਨਤੀ ਕਰਤਾ ਥਾ ਕਿ ਕੋਈ ਮੈਨੂੰ ਐਸਾ ਉਪਾਉ ਬਤਾਓ ਪੁਨਾ ਤਿਸ ਉਪਾਇ ਦ੍ਵਾਰੇ ਹਰੀ ਕਾ ਦਰਸਨ ਦਿਖਲਾਓ॥",
              "additional_information": {
                "reference": ""
              }
            },
            "Prof. Sahib Singh": {
              "translation": "ਹੇ ਹਰੀ! ਮੈਨੂੰ ਆਪਣਾ ਦਰਸਨ ਦੇਹ, ਤੂੰ ਆਪ ਹੀ ਮੈਨੂੰ ਦੱਸ (ਕਿ ਮੈਂ ਕਿਵੇਂ ਤੇਰਾ ਦਰਸਨ ਕਰਾਂ)।",
              "additional_information": {
                "arth": "ਮੋਹਿ = ਮੈਨੂੰ। ਗਲਿ = ਗਲ ਨਾਲ।",
                "note": ""
              }
            }
          },
          "Spanish": {
            "SikhNet": {
              "translation": "Oh Dios, muéstrame Tu Visión, y Revélate ante mí.",
              "additional_information": {}
            }
          }
        }
      },
      {
        "id": "F22K",
        "source_page": 408,
        "source_line": 15,
        "pronunciation": "",
        "pronunciation_information": "",
        "type": "Pankti",
        "gurmukhi": {
          "SGPC": "nwnk dIn. srix Awey; gil lwey ]2]2]153]"
        },
        "translations": {
          "English": {
            "Dr. Sant Singh Khalsa": {
              "translation": "Nanak the meek has entered Your Sanctuary; please, take me in Your embrace. ||2||2||153||",
              "additional_information": {}
            },
            "Bhai Manmohan Singh": {
              "translation": "Meek Nanak has entered Thine sanctuary, O Lord, take me in Thy embrace.",
              "additional_information": {}
            }
          },
          "Punjabi": {
            "Bhai Manmohan Singh": {
              "translation": "ਮਸਕੀਨ ਨਾਨਕ ਨੇ ਤੇਰੀ ਪਨਾਹ ਲਈ ਹੈ, ਮੈਨੂੰ ਆਪਣੇ ਗਲੇ ਨਾਲ ਲਾ ਲੈ।",
              "additional_information": {}
            },
            "Fareedkot Teeka": {
              "translation": "ਸ੍ਰੀ ਗੁਰੂ ਜੀ ਕਹਤੇ ਹੈਂ: ਜਬ ਹਮ ਇਸ ਪ੍ਰਕਾਰ ਦੀਨ ਹੋ ਕਰ ਸਤਗੁਰੋਂ ਕੀ ਸ਼ਰਣ ਆਏ ਤਬ ਹਮ ਹਰੀ ਨੇ ਗਲੇ ਸੇ ਲਗਾਇ ਲੀਏ, ਭਾਵ ਅਭਿੰਨ ਕਰ ਲੀਏ॥੨॥੨॥੧੫੩॥",
              "additional_information": {
                "reference": ""
              }
            },
            "Prof. Sahib Singh": {
              "translation": "ਹੇ ਨਾਨਕ! (ਤੂੰ ਭੀ ਅਰਜ਼ੋਈ ਕਰ, ਤੇ ਆਖ-ਹੇ ਪ੍ਰਭੂ!) ਮੈਂ ਦੀਨ ਤੇਰੀ ਸਰਨ ਆਇਆ ਹਾਂ, ਮੈਨੂੰ ਆਪਣੇ ਗਲ ਨਾਲ ਲਾ ॥੨॥੨॥੧੫੩॥",
              "additional_information": {
                "arth": "",
                "note": ""
              }
            }
          },
          "Spanish": {
            "SikhNet": {
              "translation": "El humilde Nanak ha entrado en Tu Santuario, oh Señor, tómame en Tu Regazo. (2‑21‑153)",
              "additional_information": {}
            }
          }
        }
      }
    ]
  },
  {
    "id": "BP1",
    "sttm_id": 1588,
    "writer": "Guru Arjan Dev Ji",
    "section": "Raag Aasaa",
    "subsection": null,
    "lines": [
      {
        "id": "0VS6",
        "source_page": 408,
        "source_line": 16,
        "pronunciation": "",
        "pronunciation_information": "",
        "type": "Sirlekh",
        "gurmukhi": {
          "SGPC": "Awsw mhlw 5 ]"
        },
        "translations": {
          "English": {
            "Dr. Sant Singh Khalsa": {
              "translation": "Aasaa, Fifth Mehl:",
              "additional_information": {}
            },
            "Bhai Manmohan Singh": {
              "translation": "Asa 5th Guru.",
              "additional_information": {}
            }
          },
          "Punjabi": {
            "Bhai Manmohan Singh": {
              "translation": "ਆਸਾ ਪੰਜਵੀਂ ਪਾਤਸ਼ਾਹੀ।",
              "additional_information": {}
            },
            "Fareedkot Teeka": {
              "translation": "",
              "additional_information": {
                "reference": ""
              }
            },
            "Prof. Sahib Singh": {
              "translation": "ਰਾਗ ਆਸਾ ਵਿੱਚ ਗੁਰੂ ਅਰਜਨਦੇਵ ਜੀ ਦੀ ਬਾਣੀ।",
              "additional_information": {
                "arth": "",
                "note": ""
              }
            }
          },
          "Spanish": {
            "SikhNet": {
              "translation": "Asa, Mejl Guru Aryan, Quinto Canal Divino.",
              "additional_information": {}
            }
          }
        }
      },
      {
        "id": "BZK0",
        "source_page": 408,
        "source_line": 16,
        "pronunciation": "",
        "pronunciation_information": "",
        "type": "Rahao",
        "gurmukhi": {
          "SGPC": "koaU. ibKm gwr qorY ]"
        },
        "translations": {
          "English": {
            "Dr. Sant Singh Khalsa": {
              "translation": "Who can destroy the fortress of sin,",
              "additional_information": {}
            },
            "Bhai Manmohan Singh": {
              "translation": "Can any one destroy the strong fortress of sin,",
              "additional_information": {}
            }
          },
          "Punjabi": {
            "Bhai Manmohan Singh": {
              "translation": "ਕੀ ਕੋਈ ਜਣਾ ਪਾਪ ਦੇ ਜਬਰਦਸਤ ਕਿਲੇ ਨੂੰ ਢਾਹ,",
              "additional_information": {}
            },
            "Fareedkot Teeka": {
              "translation": "ਐਸਾ ਕੋਈ ਪਰੁਖ ਹੈ, ਜੋ ਬਿਕਾਰੋਂ ਰੂਪੀ (ਬਿਖਮ) ਕਠਨ (ਗਾਰ) ਜਿਲਣ ਸੇ (ਤੋਰੈ) ਤੁਰਾਵੇ ਅਰਥਾਤ ਬਾਹਰ ਨਿਕਾਸੇ ਵਾ ਗੜ ਕੋ ਤੋੜੇ॥",
              "additional_information": {
                "reference": ""
              }
            },
            "Prof. Sahib Singh": {
              "translation": "(ਜਗਤ ਵਿਚ) ਕੋਈ ਵਿਰਲਾ ਮਨੁੱਖ ਹੈ, ਜੇਹੜਾ ਸਖ਼ਤ ਕਿਲ੍ਹੇ ਨੂੰ ਤੋੜਦਾ ਹੈ (ਜਿਸ ਵਿਚ ਜਿੰਦ ਕੈਦ ਕੀਤੀ ਪਈ ਹੈ, ਕੋਈ ਵਿਰਲਾ ਹੈ, ਜੇਹੜਾ ਆਪਣੇ ਮਨ ਨੂੰ),",
              "additional_information": {
                "arth": "ਕੋਊ = ਕੋਈ ਵਿਰਲਾ। ਬਿਖਮ = ਔਖਾ। ਗਾਰ = ਗੜ੍ਹ, ਕਿਲ੍ਹਾ। ਤੋਰੈ = ਤੋੜਦਾ ਹੈ, ਸਰ ਕਰਦਾ ਹੈ।",
                "note": ""
              }
            }
          },
          "Spanish": {
            "SikhNet": {
              "translation": "¿Puede alguien destruir la muralla del vicio y dar la espalda al engaño,",
              "additional_information": {}
            }
          }
        }
      },
      {
        "id": "1Z6V",
        "source_page": 408,
        "source_line": 16,
        "pronunciation": "",
        "pronunciation_information": "",
        "type": "Rahao",
        "gurmukhi": {
          "SGPC": "Aws ipAws Doh moh; Brm hI qy horY ]1] rhwau ]"
        },
        "translations": {
          "English": {
            "Dr. Sant Singh Khalsa": {
              "translation": "and release me from hope, thirst, deception, attachment and doubt? ||1||Pause||",
              "additional_information": {}
            },
            "Bhai Manmohan Singh": {
              "translation": "and turn himself form hope, thirst, deception, worldly love and doubt? Pause.",
              "additional_information": {}
            }
          },
          "Punjabi": {
            "Bhai Manmohan Singh": {
              "translation": "ਅਤੇ ਆਪਣੇ ਆਪ ਨੂੰ ਉਮੈਦ, ਤ੍ਰੇਹ ਧੋਖੇ, ਸੰਸਾਰੀ ਮਮਤਾ ਅਤੇ ਸੰਦੇਹੀ ਤੋਂ ਮੋੜ ਸਕਦਾ ਹੈ? ਠਹਿਰਾਉ।",
              "additional_information": {}
            },
            "Fareedkot Teeka": {
              "translation": "ਔ ਆਸਾ ਪੁਨਾ (ਪਿਆਸ) ਤ੍ਰਿਸ਼ਨਾ ਧ੍ਰੋਹ ਮੋਹ ਭ੍ਰਮ ਇਨੋਂ ਕੋ (ਹੀ) ਹਿਰਦ੍ਯ ਸੇ ਹਟਾਵੇ॥੧॥ ਰਹਾਉ ॥",
              "additional_information": {
                "reference": ""
              }
            },
            "Prof. Sahib Singh": {
              "translation": "ਦੁਨੀਆ ਦੀਆਂ ਆਸਾਂ, ਮਾਇਆ ਦੀ ਤ੍ਰਿਸ਼ਨਾ, ਠੱਗੀ-ਫ਼ਰੇਬ, ਮੋਹ ਅਤੇ ਭਟਕਣਾ ਤੋਂ ਰੋਕਦਾ ਹੈ ॥੧॥ ਰਹਾਉ ॥",
              "additional_information": {
                "arth": "ਪਿਆਸ = ਮਾਇਆ ਦੀ ਤ੍ਰਿਸ਼ਨਾ। ਧੋਹ = ਠੱਗੀ। ਭਰਮ = ਭਟਕਣਾ। ਤੇ = ਤੋਂ। ਹੋਰੈ = (ਆਪਣੇ ਮਨ ਨੂੰ) ਰੋਕਦਾ ਹੈ ॥੧॥ ਰਹਾਉ ॥",
                "note": ""
              }
            }
          },
          "Spanish": {
            "SikhNet": {
              "translation": "al amor mundano, a la duda y a la ilusión? (1‑Pausa)",
              "additional_information": {}
            }
          }
        }
      },
      {
        "id": "KRBZ",
        "source_page": 408,
        "source_line": 17,
        "pronunciation": "",
        "pronunciation_information": "",
        "type": "Pankti",
        "gurmukhi": {
          "SGPC": "kwm k®oD loB mwn; ieh ibAwiD CorY ]1]"
        },
        "translations": {
          "English": {
            "Dr. Sant Singh Khalsa": {
              "translation": "How can I escape the afflictions of sexual desire, anger, greed and pride? ||1||",
              "additional_information": {}
            },
            "Bhai Manmohan Singh": {
              "translation": "Can one leave this disease of lust, wrath, avarice and pride.",
              "additional_information": {}
            }
          },
          "Punjabi": {
            "Bhai Manmohan Singh": {
              "translation": "ਕੀ ਉਹ ਵਿਸ਼ੇ ਭੋਗ, ਗੁੱਸੇ, ਲਾਲਚ ਅਤੇ ਹੰਕਾਰ ਦੀ ਇਹ ਬੀਮਾਰੀ ਨੂੰ ਛੱਡ ਸਕਦਾ ਹੈ?",
              "additional_information": {}
            },
            "Fareedkot Teeka": {
              "translation": "ਕਾਮ, ਕ੍ਰੋਧ, ਲੋਭ ,ਮਾਨ, ਇਤ੍ਯਾਦ ਬਿਆਧੀਓਂ ਕੋ ਛੋੜ ਦੇਵੈ ਵਾ ਹਮ ਕੋ ਛੁਡਾਇ ਦੇਵੈ॥੧॥☬ਇਸ ਕੇ ਛੋੜਨੇ ਕਾ ਉਪਾਇ ਕਹਤੇ ਹੈਂ:",
              "additional_information": {
                "reference": ""
              }
            },
            "Prof. Sahib Singh": {
              "translation": "(ਜਗਤ ਵਿਚ ਕੋਈ ਵਿਰਲਾ ਮਨੁੱਖ ਹੈ ਜੇਹੜਾ) ਕਾਮ ਕ੍ਰੋਧ ਲੋਭ ਅਹੰਕਾਰ ਆਦਿਕ ਬੀਮਾਰੀਆਂ (ਆਪਣੇ ਅੰਦਰੋਂ) ਦੂਰ ਕਰਦਾ ਹੈ ॥੧॥",
              "additional_information": {
                "arth": "ਬਿਆਧਿ = ਬੀਮਾਰੀਆਂ, ਰੋਗ। ਛੋਰੈ = ਛੱਡਦਾ ਹੈ ॥੧॥",
                "note": ""
              }
            }
          },
          "Spanish": {
            "SikhNet": {
              "translation": "¿Puede alguien dejar la enfermedad de la lujuria, el enojo, la avaricia y el orgullo? (1)",
              "additional_information": {}
            }
          }
        }
      },
      {
        "id": "UF2Y",
        "source_page": 408,
        "source_line": 17,
        "pronunciation": "",
        "pronunciation_information": "",
        "type": "Pankti",
        "gurmukhi": {
          "SGPC": "sMqsMig nwm rMig; gun goivMd gwvau ]"
        },
        "translations": {
          "English": {
            "Dr. Sant Singh Khalsa": {
              "translation": "In the Society of the Saints, love the Naam, and sing the Glorious Praises of the Lord of the Universe.",
              "additional_information": {}
            },
            "Bhai Manmohan Singh": {
              "translation": "In the saints society and the Name's love, I sing the praise of the World-Lord.",
              "additional_information": {}
            }
          },
          "Punjabi": {
            "Bhai Manmohan Singh": {
              "translation": "ਸਾਧ ਸੰਗਤ ਅਤੇ ਨਾਮ ਦੀ ਪ੍ਰੀਤ ਅੰਦਰ ਮੈਂ ਸ੍ਰਿਸ਼ਟੀ ਦੇ ਸੁਆਮੀ ਦੀ ਕੀਰਤੀ ਗਾਇਨ ਕਰਦਾ ਹਾਂ।",
              "additional_information": {}
            },
            "Fareedkot Teeka": {
              "translation": "ਸੰਤੋਂ ਕਾ ਸੰਗ ਕਰੋ, ਨਾਮ ਮੇਂ ਪ੍ਰੇਮ ਕਰੋ, ਗੋਬਿੰਦ ਕੇ ਗੁਣ ਗਾਇਨ ਕਰੋ॥",
              "additional_information": {
                "reference": ""
              }
            },
            "Prof. Sahib Singh": {
              "translation": "ਮੈਂ ਤਾਂ ਸੰਤ ਜਨਾਂ ਦੀ ਸੰਗਤਿ ਵਿਚ ਰਹਿ ਕੇ ਪਰਮਾਤਮਾ ਦੇ ਨਾਮ-ਰੰਗ ਵਿਚ ਲੀਨ ਹੋ ਕੇ ਪਰਮਾਤਮਾ ਦੇ ਗੁਣ ਗਾਂਦਾ ਰਹਿੰਦਾ ਹਾਂ,",
              "additional_information": {
                "arth": "ਸੰਗਿ = ਸੰਗਤਿ ਵਿਚ। ਰੰਗਿ = ਪਿਆਰ ਵਿਚ। ਗਾਵਉ = ਮੈਂ ਗਾਂਦਾ ਹਾਂ, ਗਾਵਉਂ।",
                "note": ""
              }
            }
          },
          "Spanish": {
            "SikhNet": {
              "translation": "Asociándome con los Santos canto siempre las Alabanzas del Señor imbuido en el Amor del Nombre.",
              "additional_information": {}
            }
          }
        }
      },
      {
        "id": "5A5R",
        "source_page": 408,
        "source_line": 18,
        "pronunciation": "",
        "pronunciation_information": "",
        "type": "Pankti",
        "gurmukhi": {
          "SGPC": "Anidno; pRB iDAwvau ]"
        },
        "translations": {
          "English": {
            "Dr. Sant Singh Khalsa": {
              "translation": "Night and day, meditate on God.",
              "additional_information": {}
            },
            "Bhai Manmohan Singh": {
              "translation": "Night and day I meditate on the Lord.",
              "additional_information": {}
            }
          },
          "Punjabi": {
            "Bhai Manmohan Singh": {
              "translation": "ਰੈਣ ਦਿਹੁੰ ਮੈਂ ਸੁਆਮੀ ਦਾ ਸਿਮਰਨ ਕਰਦਾ ਹਾਂ।",
              "additional_information": {}
            },
            "Fareedkot Teeka": {
              "translation": "ਰਾਤ ਦਿਨ ਪ੍ਰਭ ਕਾ ਧਿਆਨ ਕਰੋ॥",
              "additional_information": {
                "reference": ""
              }
            },
            "Prof. Sahib Singh": {
              "translation": "ਮੈਂ ਤਾਂ ਹਰ ਵੇਲੇ ਪਰਮਾਤਮਾ ਦਾ ਧਿਆਨ ਧਰਦਾ ਹਾਂ,",
              "additional_information": {
                "arth": "ਅਨਦਿਨੋ = ਹਰ ਰੋਜ਼। ਧਿਆਵਉ = ਮੈਂ ਸਿਮਰਦਾ ਹਾਂ।",
                "note": ""
              }
            }
          },
          "Spanish": {
            "SikhNet": {
              "translation": "Y contemplo a mi Señor siempre y para siempre, y victorioso,",
              "additional_information": {}
            }
          }
        }
      },
      {
        "id": "347R",
        "source_page": 408,
        "source_line": 18,
        "pronunciation": "",
        "pronunciation_information": "",
        "type": "Pankti",
        "gurmukhi": {
          "SGPC": "BRm BIiq; jIiq imtwvau ]"
        },
        "translations": {
          "English": {
            "Dr. Sant Singh Khalsa": {
              "translation": "I have captured and demolished the walls of doubt.",
              "additional_information": {}
            },
            "Bhai Manmohan Singh": {
              "translation": "I capture and demolish the rampart of doubt.",
              "additional_information": {}
            }
          },
          "Punjabi": {
            "Bhai Manmohan Singh": {
              "translation": "ਮੈਂ ਵਹਿਮ ਦੀ ਫਸੀਲ ਨੂੰ ਫ਼ਤਿਹ ਕਰਕੇ ਮਿਟਾ ਦਿੰਦਾ ਹਾਂ।",
              "additional_information": {}
            },
            "Fareedkot Teeka": {
              "translation": "ਭ੍ਰਮ ਕੀ ਦੀਵਾਰ ਕੋ ਮਨ ਸੇ ਦੂਰ ਕਰੋ ਤਬ ਜੀਤ ਹੋਵੇਗੀ॥",
              "additional_information": {
                "reference": ""
              }
            },
            "Prof. Sahib Singh": {
              "translation": "ਤੇ ਇਸ ਤਰ੍ਹਾਂ ਭਟਕਣਾ ਦੀ ਕੰਧ ਨੂੰ ਜਿੱਤ ਕੇ (ਪਰਮਾਤਮਾ ਨਾਲੋਂ ਬਣੀ ਵਿੱਥ) ਮਿਟਾਂਦਾ ਹਾਂ।",
              "additional_information": {
                "arth": "ਭ੍ਰਮ = ਭਟਕਣਾ। ਭੀਤਿ = ਕੰਧ। ਜੀਤਿ = ਜਿੱਤ ਕੇ।",
                "note": ""
              }
            }
          },
          "Spanish": {
            "SikhNet": {
              "translation": "le gano a mi duda y destruyo sus paredes.",
              "additional_information": {}
            }
          }
        }
      },
      {
        "id": "FF9Z",
        "source_page": 408,
        "source_line": 18,
        "pronunciation": "",
        "pronunciation_information": "",
        "type": "Pankti",
        "gurmukhi": {
          "SGPC": "iniD nwmu nwnk morY ]2]3]154]"
        },
        "translations": {
          "English": {
            "Dr. Sant Singh Khalsa": {
              "translation": "O Nanak, the Naam is my only treasure. ||2||3||154||",
              "additional_information": {}
            },
            "Bhai Manmohan Singh": {
              "translation": "Nanak, the Lord's Name is my treasure.",
              "additional_information": {}
            }
          },
          "Punjabi": {
            "Bhai Manmohan Singh": {
              "translation": "ਨਾਨਕ, ਸਾਹਿਬ ਦਾ ਨਾਮ ਮੇਰਾ ਖ਼ਜ਼ਾਨਾ ਹੈ।",
              "additional_information": {}
            },
            "Fareedkot Teeka": {
              "translation": "ਸ੍ਰੀ ਗੁਰ ਜੀ ਕਹਤੇ ਹੈਂ: ਮੇਰੇ ਤੋ ਸਰਬ ਨਿਧੀ ਰੂਪ ਨਾਮ ਹੀ ਹੈ॥੨॥੩॥੧੫੪॥",
              "additional_information": {
                "reference": ""
              }
            },
            "Prof. Sahib Singh": {
              "translation": "ਹੇ ਨਾਨਕ! ਇਹਨਾਂ ਰੋਗਾਂ ਤੋਂ ਬਚਣ ਵਾਸਤੇ, ਮੇਰੇ ਪਾਸ ਪਰਮਾਤਮਾ ਦਾ ਨਾਮ-ਖ਼ਜ਼ਾਨਾ ਹੀ ਹੈ (ਜੋ ਮੈਨੂੰ ਵਿਕਾਰਾਂ ਤੋਂ ਬਚਾਈ ਰੱਖਦਾ ਹੈ) ॥੨॥੩॥੧੫੪॥",
              "additional_information": {
                "arth": "ਨਿਧਿ = ਖ਼ਜ਼ਾਨਾ। ਮੋਰੈ = ਮੇਰੈ ਪਾਸ, ਮੇਰੇ ਹਿਰਦੇ ਵਿਚ ॥੨॥੩॥੧੫੪॥",
                "note": ""
              }
            }
          },
          "Spanish": {
            "SikhNet": {
              "translation": "Dice Nanak, así he obtenido el Tesoro del Naam, el Nombre del Señor. (2‑3‑154)",
              "additional_information": {}
            }
          }
        }
      }
    ]
  },
  {
    "id": "ZED",
    "sttm_id": 1589,
    "writer": "Guru Arjan Dev Ji",
    "section": "Raag Aasaa",
    "subsection": null,
    "lines": [
      {
        "id": "QSDK",
        "source_page": 408,
        "source_line": 19,
        "pronunciation": "",
        "pronunciation_information": "",
        "type": "Sirlekh",
        "gurmukhi": {
          "SGPC": "Awsw mhlw 5 ]"
        },
        "translations": {
          "English": {
            "Dr. Sant Singh Khalsa": {
              "translation": "Aasaa, Fifth Mehl:",
              "additional_information": {}
            },
            "Bhai Manmohan Singh": {
              "translation": "Asa 5th Guru.",
              "additional_information": {}
            }
          },
          "Punjabi": {
            "Bhai Manmohan Singh": {
              "translation": "ਆਸਾ ਪੰਜਵੀਂ ਪਾਤਸ਼ਾਹੀ।",
              "additional_information": {}
            },
            "Fareedkot Teeka": {
              "translation": "",
              "additional_information": {
                "reference": ""
              }
            },
            "Prof. Sahib Singh": {
              "translation": "ਰਾਗ ਆਸਾ ਵਿੱਚ ਗੁਰੂ ਅਰਜਨਦੇਵ ਜੀ ਦੀ ਬਾਣੀ।",
              "additional_information": {
                "arth": "",
                "note": ""
              }
            }
          },
          "Spanish": {
            "SikhNet": {
              "translation": "Asa, Mejl Guru Aryan, Quinto Canal Divino.",
              "additional_information": {}
            }
          }
        }
      },
      {
        "id": "H34V",
        "source_page": 408,
        "source_line": 19,
        "pronunciation": "",
        "pronunciation_information": "",
        "type": "Rahao",
        "gurmukhi": {
          "SGPC": "kwmu k®oDu loBu iqAwgu ]"
        },
        "translations": {
          "English": {
            "Dr. Sant Singh Khalsa": {
              "translation": "Renounce sexual desire, anger and greed;",
              "additional_information": {}
            },
            "Bhai Manmohan Singh": {
              "translation": "Abandon lust, wrath and avarice,",
              "additional_information": {}
            }
          },
          "Punjabi": {
            "Bhai Manmohan Singh": {
              "translation": "ਭੋਗ ਬਿਲਾਸ, ਰੋਹ ਅਤੇ ਤਮ੍ਹਾ ਨੂੰ ਛੱਡ ਦੇ,",
              "additional_information": {}
            },
            "Fareedkot Teeka": {
              "translation": "ਕਾਮ ਕ੍ਰੋਧ ਲੋਭ ਕਾ ਤਿਆਗ ਕਰ॥",
              "additional_information": {
                "reference": ""
              }
            },
            "Prof. Sahib Singh": {
              "translation": "ਕਾਮ ਕ੍ਰੋਧ ਅਤੇ ਲੋਭ ਦੂਰ ਕਰ ਲੈ।",
              "additional_information": {
                "arth": "ਤਿਆਗੁ = ਛੱਡ ਦੇ।",
                "note": ""
              }
            }
          },
          "Spanish": {
            "SikhNet": {
              "translation": "Abandona ya tu lujuria, enojo y avaricia",
              "additional_information": {}
            }
          }
        }
      },
      {
        "id": "GQ6K",
        "source_page": 408,
        "source_line": 19,
        "pronunciation": "",
        "pronunciation_information": "",
        "type": "Rahao",
        "gurmukhi": {
          "SGPC": "min ismir. goibMd nwm ]"
        },
        "translations": {
          "English": {
            "Dr. Sant Singh Khalsa": {
              "translation": "remember the Name of the Lord of the Universe in your mind.",
              "additional_information": {}
            },
            "Bhai Manmohan Singh": {
              "translation": "remember the Name of the World Master in thy heart.",
              "additional_information": {}
            }
          },
          "Punjabi": {
            "Bhai Manmohan Singh": {
              "translation": "ਅਤੇ ਆਪਣੇ ਦਿਲ ਅੰਦਰ ਜਗਤ ਦੇ ਮਾਲਕ ਦੇ ਨਾਮ ਦਾ ਆਰਾਧਨ ਕਰ।",
              "additional_information": {}
            },
            "Fareedkot Teeka": {
              "translation": "ਮਨ ਕਰ ਕੇ ਗੋਬਿੰਦ ਨਾਮ ਕਾ ਸਿਮਰਨ ਕਰ॥",
              "additional_information": {
                "reference": ""
              }
            },
            "Prof. Sahib Singh": {
              "translation": "(ਆਪਣੇ) ਮਨ ਵਿਚ ਪਰਮਾਤਮਾ ਦਾ ਨਾਮ ਸਿਮਰਦਾ ਰਹੁ,",
              "additional_information": {
                "arth": "ਮਨਿ = ਮਨ ਵਿਚ।",
                "note": ""
              }
            }
          },
          "Spanish": {
            "SikhNet": {
              "translation": "y canta el Nombre de tu Señor en tu mente, l",
              "additional_information": {}
            }
          }
        }
      },
      {
        "id": "VAXH",
        "source_page": 408,
        "source_line": 19,
        "pronunciation": "",
        "pronunciation_information": "",
        "type": "Rahao",
        "gurmukhi": {
          "SGPC": "hir Bjn sPl kwm ]1] rhwau ]"
        },
        "translations": {
          "English": {
            "Dr. Sant Singh Khalsa": {
              "translation": "Meditation on the Lord is the only fruitful action. ||1||Pause||",
              "additional_information": {}
            },
            "Bhai Manmohan Singh": {
              "translation": "God's meditation is the only fruitful affair. Pause.",
              "additional_information": {}
            }
          },
          "Punjabi": {
            "Bhai Manmohan Singh": {
              "translation": "ਕੇਵਲ ਵਾਹਿਗੁਰੂ ਦੀ ਬੰਦਗੀ ਹੀ ਫਲਦਾਇਕ ਕੰਮ ਹੈ। ਠਹਿਰਾਉ।",
              "additional_information": {}
            },
            "Fareedkot Teeka": {
              "translation": "ਇਸ ਪ੍ਰਕਾਰ ਹਰਿ ਕਾ ਭਜਨ ਕਰਨੇ ਸੇ ਸਭ ਕਾਮ ਸਫਲ ਹੋਏਂਗੇ॥੧॥ ਰਹਾਉ ॥",
              "additional_information": {
                "reference": ""
              }
            },
            "Prof. Sahib Singh": {
              "translation": "ਪਰਮਾਤਮਾ ਦੇ ਸਿਮਰਨ ਨਾਲ ਸਾਰੇ ਕੰਮ ਸਫਲ ਹੋ ਜਾਂਦੇ ਹਨ ॥੧॥ ਰਹਾਉ ॥",
              "additional_information": {
                "arth": "ਕਾਮ = (ਸਾਰੇ) ਕੰਮ ॥੧॥ ਰਹਾਉ ॥",
                "note": ""
              }
            }
          },
          "Spanish": {
            "SikhNet": {
              "translation": "a Meditación en el Señor es la única acción fructífera. (1-Pausa) P. 409.",
              "additional_information": {}
            }
          }
        }
      },
      {
        "id": "KNF2",
        "source_page": 409,
        "source_line": 1,
        "pronunciation": "",
        "pronunciation_information": "",
        "type": "Pankti",
        "gurmukhi": {
          "SGPC": "qij mwn moh. ivkwr imiQAw; jip rwm rwm rwm ]"
        },
        "translations": {
          "English": {
            "Dr. Sant Singh Khalsa": {
              "translation": "Renounce pride, attachment, corruption and falsehood, and chant the Name of the Lord, Raam, Raam, Raam.",
              "additional_information": {}
            },
            "Bhai Manmohan Singh": {
              "translation": "Shed thy pride, worldly-love, sin and falsehood and ever utter the Pervading Lord's Name.",
              "additional_information": {}
            }
          },
          "Punjabi": {
            "Bhai Manmohan Singh": {
              "translation": "ਆਪਣੇ ਹੰਕਾਰ ਸੰਸਾਰੀ ਮਮਤਾ, ਪਾਪ ਅਤੇ ਝੂਠ ਨੂੰ ਛੱਡ ਦੇ ਅਤੇ ਹਮੇਸ਼ਾਂ ਵਿਆਪਕ ਸੁਆਮੀ ਦੇ ਨਾਮ ਦਾ ਊਚਾਰਨ ਕਰ।",
              "additional_information": {}
            },
            "Fareedkot Teeka": {
              "translation": "ਮਾਨ ਮੋਹਾਦਿ ਮਿਥ੍ਯਾ ਬਿਕਾਰੋਂ ਕੋ ਤ੍ਯਾਗ ਕਰ ਕੇ ਰਾਮ ਰਾਮ ਰਾਮ ਸਿਮਰਨ ਕਰ ਵਾ ਮਨ ਤਨ ਬਾਣੀ ਕਰ ਸਿਮਰਨ ਕਰੋ॥",
              "additional_information": {
                "reference": ""
              }
            },
            "Prof. Sahib Singh": {
              "translation": "ਅਹੰਕਾਰ ਮੋਹ ਵਿਕਾਰ ਝੂਠ ਤਿਆਗ ਦੇਹ, ਸਦਾ ਪਰਮਾਤਮਾ ਦਾ ਸਿਮਰਨ ਕਰਿਆ ਕਰ,",
              "additional_information": {
                "arth": "ਤਜਿ = ਤਿਆਗ ਦੇ। ਮਿਥਿਆ = ਝੂਠ।",
                "note": ""
              }
            }
          },
          "Spanish": {
            "SikhNet": {
              "translation": "Renuncia al orgullo, apego, corrupción y falsedad y canta el Naam, el Nombre del Señor, Ram, Ram, Ram,",
              "additional_information": {}
            }
          }
        }
      },
      {
        "id": "TEDW",
        "source_page": 409,
        "source_line": 1,
        "pronunciation": "",
        "pronunciation_information": "",
        "type": "Pankti",
        "gurmukhi": {
          "SGPC": "mn; sMqnw kY crin lwgu ]1]"
        },
        "translations": {
          "English": {
            "Dr. Sant Singh Khalsa": {
              "translation": "O mortal, attach yourself to the Feet of the Saints. ||1||",
              "additional_information": {}
            },
            "Bhai Manmohan Singh": {
              "translation": "O man, attach thyself to the saints' feet.",
              "additional_information": {}
            }
          },
          "Punjabi": {
            "Bhai Manmohan Singh": {
              "translation": "ਹੇ ਬੰਦੇ! ਤੂੰ ਆਪਣੇ ਆਪ ਨੂੰ ਸਾਧੂਆਂ ਦੇ ਪੈਰਾਂ ਨਾਲ ਜੋੜ।",
              "additional_information": {}
            },
            "Fareedkot Teeka": {
              "translation": "ਔਰ ਮਨ ਕਰ ਸੰਤ ਜਨਾਂ ਕੇ ਚਰਨੋਂ ਮੇਂ ਲਾਗ॥੧॥",
              "additional_information": {
                "reference": ""
              }
            },
            "Prof. Sahib Singh": {
              "translation": "ਹੇ ਮਨ! ਤੇ ਸੰਤ ਜਨਾਂ ਦੀ ਸਰਨ ਪਿਆ ਰਹੁ ॥੧॥",
              "additional_information": {
                "arth": "ਮਨ = ਹੇ ਮਨ! ਕੈ ਚਰਨਿ = ਦੇ ਚਰਨ ਵਿਚ ॥੧॥",
                "note": ""
              }
            }
          },
          "Spanish": {
            "SikhNet": {
              "translation": "oh mortal y aférrate a los Pies de los Santos. (1)",
              "additional_information": {}
            }
          }
        }
      },
      {
        "id": "TWZ5",
        "source_page": 409,
        "source_line": 2,
        "pronunciation": "",
        "pronunciation_information": "",
        "type": "Pankti",
        "gurmukhi": {
          "SGPC": "pRB gopwl dIn dieAwl, piqq. pwvn pwrbRhm; hir crx ismir. jwgu ]"
        },
        "translations": {
          "English": {
            "Dr. Sant Singh Khalsa": {
              "translation": "God is the Sustainer of the world, Merciful to the meek, the Purifier of sinners, the Transcendent Lord God. Awaken, and meditate on His Feet.",
              "additional_information": {}
            },
            "Bhai Manmohan Singh": {
              "translation": "The Lord is the Cherisher of the world, merciful to the poor. the Purifier of the sinners and thy Transcendent God. Awake and remember His Feet.",
              "additional_information": {}
            }
          },
          "Punjabi": {
            "Bhai Manmohan Singh": {
              "translation": "ਠਾਕੁਰ, ਜਗਤ ਦਾ ਪਾਲਣਹਾਰ, ਗਰੀਬਾਂ ਤੇ ਮਿਹਰਬਾਨ, ਪਾਪੀਆਂ ਨੂੰ ਪਵਿੱਤਰ ਕਰਨ ਵਾਲਾ ਅਤੇ ਤੇਰਾ ਪਰਮ ਵਾਹਿਗੁਰੂ ਹੈ। ਨੀਦ ਤਿਆਗ ਅਤੇ ਉਸ ਦੇ ਪੈਰਾਂ ਦਾ ਆਰਾਧਨ ਕਰ।",
              "additional_information": {}
            },
            "Fareedkot Teeka": {
              "translation": "ਪ੍ਰਭੁ ਗੋਪਾਲ ਦੀਨ ਦਿਆਲ ਪਤਿਤ ਪਾਵਨ ਹਰਿ ਪਾਰਬ੍ਰਹਮ ਕੇ ਚਰਣੋਂ ਕਾ ਸਿਮਰਣ ਕਰ ਕੇ ਮੋਹੁ ਨਿੰਦ੍ਰਾ ਸੇ ਜਾਗੁ॥",
              "additional_information": {
                "reference": ""
              }
            },
            "Prof. Sahib Singh": {
              "translation": "ਉਸ ਹਰੀ-ਪ੍ਰਭੂ ਦੇ ਚਰਨਾਂ ਦਾ ਧਿਆਨ ਧਰ ਕੇ (ਮਾਇਆ ਦੇ ਹੱਲਿਆਂ ਵਲੋਂ) ਸੁਚੇਤ ਰਹੁ ਜੋ ਧਰਤੀ ਦਾ ਰਾਖਾ ਹੈ ਜੋ ਦੀਨਾਂ ਉਤੇ ਦਇਆ ਕਰਨ ਵਾਲਾ ਹੈ ਅਤੇ ਜੋ ਵਿਕਾਰਾਂ ਵਿਚ ਡਿੱਗੇ ਹੋਏ ਬੰਦਿਆਂ ਨੂੰ ਪਵ੍ਰਿਤ ਕਰਨ ਵਾਲਾ ਹੈ।",
              "additional_information": {
                "arth": "ਗੋਪਾਲ = ਸ੍ਰਿਸ਼ਟੀ ਦਾ ਪਾਲਕ। ਪਤਿਤ = ਵਿਕਾਰਾਂ ਵਿਚ ਡਿੱਗੇ ਹੋਏ। ਪਾਵਨ = ਪਵਿਤ੍ਰ (ਕਰਨ ਵਾਲਾ)। ਜਾਗੁ = (ਵਿਕਾਰਾਂ ਵਲੋਂ) ਸੁਚੇਤ ਰਹੁ।",
                "note": ""
              }
            }
          },
          "Spanish": {
            "SikhNet": {
              "translation": "Tu Señor es Compasivo con los pobres, el Sostenedor de la Tierra, es el Purificador de los que cometen faltas, tu Dios Supremo, despierta, oh mi mente, y contempla los Pies de tu Señor.",
              "additional_information": {}
            }
          }
        }
      },
      {
        "id": "V9EC",
        "source_page": 409,
        "source_line": 2,
        "pronunciation": "",
        "pronunciation_information": "",
        "type": "Pankti",
        "gurmukhi": {
          "SGPC": "kir Bgiq; nwnk. pUrn Bwgu ]2]4]155]"
        },
        "translations": {
          "English": {
            "Dr. Sant Singh Khalsa": {
              "translation": "Perform His devotional worship, O Nanak, and your destiny shall be fulfilled. ||2||4||155||",
              "additional_information": {}
            },
            "Bhai Manmohan Singh": {
              "translation": "Perform Lord's Devotional Service thy destiny shall become perfect, O Nanak.",
              "additional_information": {}
            }
          },
          "Punjabi": {
            "Bhai Manmohan Singh": {
              "translation": "ਸੁਆਮੀ ਦੀ ਪ੍ਰੇਮ-ਮਈ ਸੇਵਾ ਕਰ ਅਤੇ ਤੇਰੀ ਕਿਸਮਤ ਮੁਕੰਮਲ ਥੀ ਵੰਞੇਗੀ, ਹੇ ਨਾਨਕ।",
              "additional_information": {}
            },
            "Fareedkot Teeka": {
              "translation": "ਸ੍ਰੀ ਗੁਰੂ ਜੀ ਕਹਤੇ ਹੈਂ: ਹਰਿ ਕੀ ਭਗਤਿ ਕਰੁ, ਪਰੰਤੂ ਪੂਰਨ ਭਾਗਾਂ ਸੇ ਹਰੀ ਕੀ ਭਗਤੀ ਮਿਲਤੀ ਹੈ॥੨॥੪॥੧੫੫॥☬ਮਾਯਾ ਅਨੇਕ ਪ੍ਰਕਾਰ ਕਰ ਮਨ ਕੋ ਭ੍ਰਮਾਵਤੀ ਹੈ। ਇਸ ਬਾਤ ਕੋ ਦਿਖਾਵਤੇ ਹੂਏ ਕਹਤੇ ਹੈਂ:",
              "additional_information": {
                "reference": ""
              }
            },
            "Prof. Sahib Singh": {
              "translation": "ਹੇ ਨਾਨਕ! (ਆਖ-ਹੇ ਭਾਈ!) ਪਰਮਾਤਮਾ ਦੀ ਭਗਤੀ ਕਰ, ਤੇਰੀ ਕਿਸਮਤ ਜਾਗ ਪਏਗੀ ॥੨॥੪॥੧੫੫॥",
              "additional_information": {
                "arth": "ਭਾਗੁ = ਕਿਸਮਤ ॥੨॥੪॥੧੫੫॥",
                "note": ""
              }
            }
          },
          "Spanish": {
            "SikhNet": {
              "translation": "Sí, alaba a tu Señor para que tu Destino se vuelva Perfecto. (2-4-155)",
              "additional_information": {}
            }
          }
        }
      }
    ]
  }
]
