{
  "content": [
    {
      "asset": "ssa2",
      "type": "primary",
      "data": "ਜਿਸੁ ਪੇਖਤ. ਕਿਲਵਿਖ ਹਿਰਹਿ; ਮਨਿ ਤਨਿ ਹੋਵੈ ਸਾਂਤਿ ॥",
      "page": 47,
      "line": 3
    },
    {
      "asset": "sbms",
      "type": "translation",
      "language": "en",
      "data": "By seeing the Lord, the soul and body are rendered peaceful."
    },
    {
      "asset": "sbms",
      "type": "translation",
      "language": "pa",
      "data": "ਜਿਸ ਨੂੰ ਵੇਖਣ ਦੁਆਰਾ ਪਾਪ ਅਲੋਪ ਹੋ ਜਾਂਦੇ ਹਨ, ਆਤਮਾ ਤੇ ਦੇਹਿ ਸੀਤਲ ਹੋ ਜਾਂਦੇ ਹਨ,"
    },
    {
      "asset": "dssk",
      "type": "translation",
      "language": "en",
      "data": "Seeing Him, our evil inclinations vanish; mind and body become peaceful and tranquil."
    },
    {
      "asset": "nkft",
      "type": "translation",
      "language": "pa",
      "data": "ਜਿਸ ਕੇ ਦਰਸਨ ਮਾਤ੍ਰ ਸੇ ਹੀ (ਕਿਲਵਿਖ) ਪਾਪ (ਹਿਰਹਿ) ਨਾਸ ਹੋਤੇ ਹੈਂ, ਮਨ ਤਨ ਮੇਂ ਸਾਂਤਿ ਪ੍ਰਾਪਤਿ ਹੋਤੀ ਹੈ॥"
    },
    {
      "asset": "psst",
      "type": "translation",
      "language": "pa",
      "data": "(ਹੇ ਭਾਈ!) ਜਿਸ ਪਰਮਾਤਮਾ ਦਾ ਦਰਸਨ ਕੀਤਿਆਂ (ਸਾਰੇ) ਪਾਪ ਨਾਸ ਹੋ ਜਾਂਦੇ ਹਨ, (ਜਿਸ ਦੇ ਦਰਸਨ ਨਾਲ) ਮਨ ਵਿਚ ਤੇ ਸਰੀਰ ਵਿਚ (ਆਤਮਕ) ਠੰਡ ਪੈ ਜਾਂਦੀ ਹੈ,"
    },
    {
      "asset": "snst",
      "type": "translation",
      "language": "es",
      "data": "Teniendo Su Visión, nuestros errores se limpian y nuestro cuerpo y mente descansan en Paz."
    }
  ]
}