{
  "content": [
    {
      "asset": "SSA2",
      "type": "primary",
      "data": "ਸਾਧਸੰਗਿ; ਹਰਿ ਕੀਰਤਨੁ ਗਾਈਐ ॥",
      "page": 385,
      "line": 17
    },
    {
      "asset": "SBMS",
      "type": "translation",
      "language": "en",
      "data": "In the society of saints sing the praise of God."
    },
    {
      "asset": "SBMS",
      "type": "translation",
      "language": "pa",
      "data": "ਸਤਿ ਸੰਗਤ ਅੰਦਰ ਵਾਹਿਗੁਰੂ ਦਾ ਜੱਸ ਗਾਇਨ ਕਰ।"
    },
    {
      "asset": "DSSK",
      "type": "translation",
      "language": "en",
      "data": "In the Saadh Sangat, the Company of the Holy, sing the Kirtan of the Lord's Praises."
    },
    {
      "asset": "NKFT",
      "type": "translation",
      "language": "pa",
      "data": "ਸਤਸੰਗਿ ਕਰ ਕੇ ਹਰਿ ਕਾ ਗਾਇਨ ਕਰੀਏ॥"
    },
    {
      "asset": "PSST",
      "type": "translation",
      "language": "pa",
      "data": "(ਹੇ ਮਿੱਤਰ!) ਸਾਧ ਸੰਗਤਿ ਵਿਚ ਰਹਿ ਕੇ (ਸਦਾ) ਪਰਮਾਤਮਾ ਦੀ ਸਿਫ਼ਤਿ-ਸਾਲਾਹ ਕਰਦੇ ਰਹਿਣਾ ਚਾਹੀਦਾ ਹੈ (ਇਸ ਦੀ ਬਰਕਤਿ ਨਾਲ ਹਉਮੈ, ਮਾਇਆ ਦਾ ਮੋਹ, ਚਿੰਤਾ, ਅਹੰਕਾਰ ਦੇ ਜੰਜਾਲ ਆਦਿਕ ਕੋਈ ਭੀ ਪੋਹ ਨਹੀਂ ਸਕਦਾ)"
    },
    {
      "asset": "SNST",
      "type": "translation",
      "language": "es",
      "data": "Si cantamos simple y sencillamente las Alabanzas del Señor en la Sociedad de los Santos,"
    }
  ]
}