{
  "content": [
    {
      "asset": "DGDG",
      "type": "primary",
      "data": "ਭਉਨਨ ਤੇ ਸਭ ਇਉ ਨਿਕਰੀ; ਜਿਮੁ ਮੰਤ੍ਰ ਪੜ੍ਰਹੇ ਨਿਕਰੈ ਬਹੁ ਨਾਗਨ ॥੩੧੫॥",
      "page": 324
    },
    {
      "asset": "DSKO",
      "type": "translation",
      "language": "en",
      "data": "They have come out of their houses like the female serpents under the control of mantras.315."
    },
    {
      "asset": "RSJD",
      "type": "translation",
      "language": "pa",
      "data": "ਘਰਾਂ ਵਿਚੋਂ (ਉਹ ਇਸਤਰੀਆਂ) ਇਉਂ ਨਿਕਲੀਆਂ ਹਨ ਜਿਵੇਂ ਮੰਤ੍ਰ ਪੜ੍ਹਨ ਨਾਲ ਬਹੁਤ ਸਾਰੀਆਂ ਨਾਗਣਾਂ ਨਿਕਲ ਆਉਂਦੀਆਂ ਹਨ ॥੩੧੫॥"
    }
  ]
}