{
  "content": [
    {
      "asset": "DGDG",
      "type": "primary",
      "data": "ਮਾਨਹੁ ਦੇਖਨ ਕਉ ਰਨ ਕਉਤੁਕ; ਕ੍ਰੋਧ ਭਿਆਨਕ ਰੂਪ ਧਰਿਓ ਹੈ ॥੧੭੬੬॥",
      "page": 474
    },
    {
      "asset": "DSKO",
      "type": "translation",
      "language": "en",
      "data": "That the ‘anger’ had manifested himself apparently in order to see the war-scenes.1766."
    },
    {
      "asset": "RSJD",
      "type": "translation",
      "language": "pa",
      "data": "ਮਾਨੋ ਯੁੱਧ ਦੇ ਕੌਤਕ ਨੂੰ ਵੇਖਣ ਲਈ ਕ੍ਰੋਧ ਨੇ ਭਿਆਨਕ ਰੂਪ ਧਾਰਨ ਕੀਤਾ ਹੋਵੇ ॥੧੭੬੬॥"
    }
  ]
}
