[
  {
    "SHABAD_ID": 11393,
    "LINE_ID": 1,
    "RAAG_ID": 52,
    "GURMUKHI": "gÍwrn rIJ rhI hir pyiK sBY qij lwij su Aau fr swso ] AweI hY iqAwg soaU giH pY Brqwr khy n kCU kih mwso ]",
    "TRANSLITERATION": "Gvaaran Reejh Rahihar(i) Pekh(i) Sabhai Taj(i) Laaj(i) Su Au Dar Saaso|| Ooihai Tiaag Sooo Grih Pai Bharttaar Kahe Na Kachhodh Kah(i) Maaso||",
    "PUNJABI": "",
    "PRONUNCIATION": null
  },
  {
    "SHABAD_ID": 11393,
    "LINE_ID": 2,
    "RAAG_ID": 52,
    "GURMUKHI": "folq hY soaU qwl bjwie kY gwvq hY kir kY auphwso ] moih igrY Dr pY su qRIXw kib sXwm khY icqvY hir jwso ]606]",
    "TRANSLITERATION": "Dolat Hai Sooo Taal Bajaae Kai Gadvat Hai Kar(i) Kai Oup-haaso|| Moh(i) Giraidhar Pai Su Treeyaa Kabi Syaam Kahai Chitvai Har(i) Jaaso||606||",
    "PUNJABI": "",
    "PRONUNCIATION": null
  },
  {
    "SHABAD_ID": 11394,
    "LINE_ID": 3,
    "RAAG_ID": 52,
    "GURMUKHI": "svYXw ]",
    "TRANSLITERATION": "Sawaiyaa||",
    "PUNJABI": "",
    "PRONUNCIATION": null
  },
  {
    "SHABAD_ID": 11394,
    "LINE_ID": 4,
    "RAAG_ID": 52,
    "GURMUKHI": "jo jug qIsr hY krqw joaU hY qn pY DrIXw pt pIly ] jwih ClXo bilrwj blI ijn SqR hny kr kop hTIly ]",
    "TRANSLITERATION": "Jo Joug Teesar Hai Kartaa Jooo Hai Tan Pai Ddareeyaa Pat Peele|| Jaah(i) Chhalyo Baliraaj Balishatra Hane Kar Kop Hatheele||",
    "PUNJABI": "",
    "PRONUNCIATION": null
  },
  {
    "SHABAD_ID": 11394,
    "LINE_ID": 5,
    "RAAG_ID": 52,
    "GURMUKHI": "gÍwrn rIJ rhI DrnI ju Dry pt pIqn pY su rMgIly ] ijau miRgnI sr lwg igrY ieh iqau hir dyKq nYn rsIly ]607]",
    "TRANSLITERATION": "Gvaaran Reejh Rahidharniju Ddare Pat Peetan Pai Su Raneele|| Jio Mrigadisar Laag Girai Eh Tio Har(i) Dekhat Nain Raseele||607||",
    "PUNJABI": "",
    "PRONUNCIATION": null
  },
  {
    "SHABAD_ID": 11395,
    "LINE_ID": 6,
    "RAAG_ID": 52,
    "GURMUKHI": "svYXw ]",
    "TRANSLITERATION": "Sawaiyaa||",
    "PUNJABI": "",
    "PRONUNCIATION": null
  },
  {
    "SHABAD_ID": 11395,
    "LINE_ID": 7,
    "RAAG_ID": 52,
    "GURMUKHI": "kwnHr ky sMg Kylq so Aiq hI suK ko kr kY qn mY ] sXwm hI so Aiq hI hI ihq kY icq kY nih bMDn Aau Dn mY ]",
    "TRANSLITERATION": "Kaahnar Ke San Khelat So At(i) Hisoukh Ko Kar Kai Tan Mai|| Syaam Hiso At(i) Hihit Kai Chit Kai Nah(i) Bandhan Au Dhan Mai||",
    "PUNJABI": "",
    "PRONUNCIATION": null
  },
  {
    "SHABAD_ID": 11395,
    "LINE_ID": 8,
    "RAAG_ID": 52,
    "GURMUKHI": "Dr rMgin bsqR sBy qih folq XO aupmw aupjI mn mY ] joaU PUl muKI qh PUl kY Kylq PUl sI hoie geI bn mY ]608]",
    "TRANSLITERATION": "Dhar Ranad(i) Bastra Sabhe Tah(i) Dolat Yaoun Oupmaa Oupjiman Mai|| Jooo Phool Moukhitah Phool Sihoe Gadban Mai||608||",
    "PUNJABI": "",
    "PRONUNCIATION": null
  },
  {
    "SHABAD_ID": 11396,
    "LINE_ID": 9,
    "RAAG_ID": 52,
    "GURMUKHI": "svYXw ]",
    "TRANSLITERATION": "Sawaiyaa||",
    "PUNJABI": "",
    "PRONUNCIATION": null
  },
  {
    "SHABAD_ID": 11396,
    "LINE_ID": 10,
    "RAAG_ID": 52,
    "GURMUKHI": "sB Kylq hY mn AwnMd kY Bgvwn ko Dwr sBY mn mYN ] hir ky icqby kI rhI suD eyk n Aaur rhI n kCU qn mYN ]",
    "TRANSLITERATION": "Sabh Khelat Hai Man Aanand Kai Bhagvaan Ko Dhaar Sabhai Man Main|| Har(i) Ke Chitbe Kirahisudh Ek Na Aur Rahina Kachhodh Tan Main||",
    "PUNJABI": "",
    "PRONUNCIATION": null
  },
  {
    "SHABAD_ID": 11396,
    "LINE_ID": 11,
    "RAAG_ID": 52,
    "GURMUKHI": "nhI BUqlu mYN Aru mwqlu mYN ien so nih dyvn ky gn mYN ] soaU rIJ so sXwm khY Aiq hI Pun folq gÍwrn ky gn mYN ]609]",
    "TRANSLITERATION": "Nahibhootal(u) Main Ar(u) Maatal(u) Main In So Nah(i) Devan Ke Gad Main|| Sooo Reejh So Syaam Kahai At(i) Hiphoun Dolat Gvaaran Ke Gad Main||609||",
    "PUNJABI": "",
    "PRONUNCIATION": null
  },
  {
    "SHABAD_ID": 11397,
    "LINE_ID": 12,
    "RAAG_ID": 52,
    "GURMUKHI": "svYXw ]",
    "TRANSLITERATION": "Swaiyaa||",
    "PUNJABI": "",
    "PRONUNCIATION": null
  },
  {
    "SHABAD_ID": 11397,
    "LINE_ID": 13,
    "RAAG_ID": 52,
    "GURMUKHI": "his kY Bgvwn khI bqIXw biRKBwn suqw ipK rUp nvIno ] AMgn Awf Dry pun bysr Bwv sBY ijn Bwvn kIno ]",
    "TRANSLITERATION": "Has(i) Kai Bhagvaan Kahibateeyaa Brikhbhaan Soutaa Pikh Roop Naveeno|| Anad Aad Ddare Poun Besar Bhaav Sabhai Jin Bhaavan Keeno||",
    "PUNJABI": "",
    "PRONUNCIATION": null
  },
  {
    "SHABAD_ID": 11397,
    "LINE_ID": 14,
    "RAAG_ID": 52,
    "GURMUKHI": "suMdr syNDr ko ijn lY kir Bwl ibKY ibMdUAw iek dIno ] nYn ncwie mnY suK pwie icqY jdurwie qbY his dIno ]610]",
    "TRANSLITERATION": "Soundar Sendhar Ko Jin Tai Kar(i) Dhaal Bikhai Bindooaa Ik Deeno Nain Nachaae Manai Soukh Paae Chitai Jaduraae Tabai Has(i) Dino||610||",
    "PUNJABI": "",
    "PRONUNCIATION": null
  }
]