[
  {
    "id": "U7X",
    "sttm_id": 30023,
    "writer": "Bhai Nand Lal Ji",
    "section": "Ghazals",
    "subsection": null,
    "lines": [
      {
        "id": "0QDC",
        "source_page": 24,
        "source_line": 1,
        "pronunciation": null,
        "pronunciation_information": null,
        "type": "Pankti",
        "gurmukhi": {
          "Dr. Ganda Singh": "qw lwil jwx &zwie qU goXw nmI Svd ["
        },
        "translations": {
          "English": {
            "Pritpal Singh Bindra": {
              "translation": "Because, he meditates and has only Naam of the Omnipotent on his tongue. (39) (2)",
              "additional_information": {}
            }
          },
          "Punjabi": {
            "Dr. Ganda Singh": {
              "translation": "ਜਦ ਤਕ ਤੇਰੇ ਜਾਨ ਵਧਾਉਣ ਵਾਲੇ ਲਾਲ ਹੋਠ ਬੋਲਦੇ ਨਹੀਣ,",
              "additional_information": {}
            }
          }
        }
      },
      {
        "id": "WS7U",
        "source_page": 24,
        "source_line": 1,
        "pronunciation": null,
        "pronunciation_information": null,
        "type": "Pankti",
        "gurmukhi": {
          "Dr. Ganda Singh": "drmwin drid mwsq ik pYdw nmI Svd [24[1["
        },
        "translations": {
          "English": {
            "Pritpal Singh Bindra": {
              "translation": "The fragrant black speckle, the mole, of your cheek, has enamored the entire world,   ",
              "additional_information": {}
            }
          },
          "Punjabi": {
            "Dr. Ganda Singh": {
              "translation": "ਸਾਡੈ ਦਰਦਾਣ ਦੀ ਦਵਾ ਵੀ ਪੈਦਾ ਨਹੀਣ ਹੋ ਸਕਦੀ ।",
              "additional_information": {}
            }
          }
        }
      },
      {
        "id": "UKYL",
        "source_page": 24,
        "source_line": 2,
        "pronunciation": null,
        "pronunciation_information": null,
        "type": "Pankti",
        "gurmukhi": {
          "Dr. Ganda Singh": "lib iqSnw rw bw-Awib lbq hsq AwrzU ["
        },
        "translations": {
          "English": {
            "Pritpal Singh Bindra": {
              "translation": "And, your locks of hair are just like a snare for the faith and the religion and nothing else.(39) (3) ",
              "additional_information": {}
            }
          },
          "Punjabi": {
            "Dr. Ganda Singh": {
              "translation": "ਪਿਆਸੇ ਹੋਠਾਣ ਨੂੰ ਤੇਰੇ ਹੋਠਾਣ ਦੇ ਅੰੰਿਮ੍ਰਤ ਦੀ ਲਾਲਸਾ ਹੈ ।",
              "additional_information": {}
            }
          }
        }
      },
      {
        "id": "HDFG",
        "source_page": 24,
        "source_line": 2,
        "pronunciation": null,
        "pronunciation_information": null,
        "type": "Pankti",
        "gurmukhi": {
          "Dr. Ganda Singh": "qskIin mw iz i^zro msIhw nmI Svd [24[2["
        },
        "translations": {
          "English": {
            "Pritpal Singh Bindra": {
              "translation": "O Guru! Kindly show me your sun-like face as soon as possible,",
              "additional_information": {}
            }
          },
          "Punjabi": {
            "Dr. Ganda Singh": {
              "translation": "ਸਾਡੀ ਤਸੱਲੀ ਖ਼ਿਜ਼ਰ ਜਾਣ ਮਸੀਹਾ ਤੋਣ ਭੀ ਨਹੀਣ ਹੋ ਸਕਦੀ ।",
              "additional_information": {}
            }
          }
        }
      },
      {
        "id": "JFZV",
        "source_page": 24,
        "source_line": 3,
        "pronunciation": null,
        "pronunciation_information": null,
        "type": "Pankti",
        "gurmukhi": {
          "Dr. Ganda Singh": "dwrym drid idl ik mr aU rw ielwj nIsq ["
        },
        "translations": {
          "English": {
            "Pritpal Singh Bindra": {
              "translation": "Because, this is the only cure for my tearful eyes and nothing else.\" (39) (4)\nMy heart and soul is simply captivated for his handsome stature and gait,\nAnd, my life is for sacrifice to the dust of my beloved's feet.\" (39) (5)",
              "additional_information": {}
            }
          },
          "Punjabi": {
            "Dr. Ganda Singh": {
              "translation": "ਸਾਨੂੰ ਅਜੇਹਾ ਦਿਲ ਦਾ ਦਰਦ ਲੱਗਾ ਹੋਇਆ ਹੈ, ਕਿ ਜਿਸ ਦਾ ਕੋਈ ਇਲਾਜ ਨਹੀਣ ।",
              "additional_information": {}
            }
          }
        }
      },
      {
        "id": "K8FP",
        "source_page": 24,
        "source_line": 3,
        "pronunciation": null,
        "pronunciation_information": null,
        "type": "Pankti",
        "gurmukhi": {
          "Dr. Ganda Singh": "qw jwx nmI idhym mdwvw nmI Svd [24[3["
        },
        "translations": {
          "English": {
            "Pritpal Singh Bindra": {
              "translation": "Alas! I wish you had asked Goyaa even for a moment, How are you?",
              "additional_information": {}
            }
          },
          "Punjabi": {
            "Dr. Ganda Singh": {
              "translation": "ਜਦ ਤਕ ਅਸੀਣ ਜਾਨ ਨਹੀਣ ਦੇ ਦਿੰਦੇ ਆਰਾਮ ਨਹੀਣ ਹੋ ਸਕਦਾ ।",
              "additional_information": {}
            }
          }
        }
      },
      {
        "id": "74LZ",
        "source_page": 24,
        "source_line": 4,
        "pronunciation": null,
        "pronunciation_information": null,
        "type": "Pankti",
        "gurmukhi": {
          "Dr. Ganda Singh": "gu&qm ik jwx-idhym ieviz X¤k ingwih qU ["
        },
        "translations": {
          "English": {
            "Pritpal Singh Bindra": {
              "translation": "Because, this is the only remedy for my painfully tortured heart.\" (39) (6)\nAfter getting drunk (with His Naam), one should become pious and chaste,\nOne should be inebriated and become indifferent to life and an embodiment of meditation.” (40) (1)\nYou should not cast your eyes just even to look towards any one else; this will be an act of blindness;\nYou should become an eye from head to toe, and aim your vision only towards your Beloved. (40) (2)\nCircumambulate around the torso of heart-stealing king, the Guru,\nAnd, assume yourself as the prisoner of the knot of the fragrant lock of his hair.\" (40) (3)",
              "additional_information": {}
            }
          },
          "Punjabi": {
            "Dr. Ganda Singh": {
              "translation": "ਮੈਣ ਆਖਿਆ, ਤੇਰੀ ਇੱਕ ਨਿਗਾਹ ਬਦਲੇ ਅਸੀਣ ਜਾਨ ਹਾਜ਼ਰ ਕਰਦੇ ਹਾਣ,",
              "additional_information": {}
            }
          }
        }
      },
      {
        "id": "V93K",
        "source_page": 24,
        "source_line": 4,
        "pronunciation": null,
        "pronunciation_information": null,
        "type": "Pankti",
        "gurmukhi": {
          "Dr. Ganda Singh": "gu&qw imAwin mw E qU sOdw nmI Svd [24[4["
        },
        "translations": {
          "English": {
            "Pritpal Singh Bindra": {
              "translation": "I am not asking anyone to go to the temple or the Muslin shrine.",
              "additional_information": {}
            }
          },
          "Punjabi": {
            "Dr. Ganda Singh": {
              "translation": "ਉਸ ਆਖਿਆ, ਸਾਡੇ ਤੁਹਾਡੇ ਵਿਚਕਾਰ ਇਹ ਸੌਦਾ ਨਹੀਣ ਹੋ ਸਕਦਾ ।",
              "additional_information": {}
            }
          }
        }
      },
      {
        "id": "MLBW",
        "source_page": 24,
        "source_line": 5,
        "pronunciation": null,
        "pronunciation_information": null,
        "type": "Pankti",
        "gurmukhi": {
          "Dr. Ganda Singh": "AMdr hvwie zuli& igrwhgIr mihvSwx ["
        },
        "translations": {
          "English": {
            "Pritpal Singh Bindra": {
              "translation": "I am simply suggesting that no matter where you decide to go, you should always keep your face towards the Almighty.\" (40) (4)\nTurning away from me like a stranger, why are you are paying attention to my rivals?\nJust look towards me even for a short while and get familiar with the condition of this broken heart. (40) (5)\nGoya says, \"Become content and pleasant like my heart, And do not become indifferent after having your desires fulfilled.",
              "additional_information": {}
            }
          },
          "Punjabi": {
            "Dr. Ganda Singh": {
              "translation": "ਚੰਨ ਵਰਗੇ ਸੋਹਣਿਆਣ ਦੀਆਣ ਗੰਢਾਣ ਲੱਗੀਆਣ ਜ਼ੁਲਫ਼ਾਣ ਦੀ ਲਾਲਸਾ ਵਿਚ,",
              "additional_information": {}
            }
          }
        }
      },
      {
        "id": "VKYR",
        "source_page": 24,
        "source_line": 5,
        "pronunciation": null,
        "pronunciation_information": null,
        "type": "Pankti",
        "gurmukhi": {
          "Dr. Ganda Singh": "mn vI-rvm igrh iz idlm vw nmI Svd [24[5["
        },
        "translations": {
          "English": {
            "Pritpal Singh Bindra": {
              "translation": "In fact, rid yourself of all purpose and pursuits.(This way, one can attain the real goal) (40) (6)",
              "additional_information": {}
            }
          },
          "Punjabi": {
            "Dr. Ganda Singh": {
              "translation": "ਮੈਣ ਜਾਣਦਾ ਤਾਣ ਹਾਣ ਪਰ ਮੇਰੇ ਦਿਲ ਦੀ ਗੰਢ ਤੇਰੇ ਬਿਨਾਣ ਨਹੀਣ ਖੁਲ੍ਹਨੀ ।",
              "additional_information": {}
            }
          }
        }
      },
      {
        "id": "33M2",
        "source_page": 24,
        "source_line": 6,
        "pronunciation": null,
        "pronunciation_information": null,
        "type": "Pankti",
        "gurmukhi": {
          "Dr. Ganda Singh": "bw hwisil murwd kujw AwSnw Svym ["
        },
        "translations": {
          "English": {
            "Pritpal Singh Bindra": {
              "translation": "Hearts of everyone in deep love are scorched and charred,",
              "additional_information": {}
            }
          },
          "Punjabi": {
            "Dr. Ganda Singh": {
              "translation": "ਜਦ ਤੱਕ ਕਿ ਸਾਡੀ ਅੱਖ ਤੇਰੀ ਯਾਦ ਵਿਚ ਸਾਗਰ ਨਹੀਣ ਬਣ ਜਾਣਦੀ,",
              "additional_information": {}
            }
          }
        }
      },
      {
        "id": "FX64",
        "source_page": 24,
        "source_line": 6,
        "pronunciation": null,
        "pronunciation_information": null,
        "type": "Pankti",
        "gurmukhi": {
          "Dr. Ganda Singh": "qw cSim mw b-Xwid qU dirAw nmI Svd [24[6["
        },
        "translations": {
          "English": {
            "Pritpal Singh Bindra": {
              "translation": "Both the worlds are amazed and even desperately restless for his glimpse. (41) (1)",
              "additional_information": {}
            }
          },
          "Punjabi": {
            "Dr. Ganda Singh": {
              "translation": "ਅਸੀਣ ਮੁਰਾਦ ਦੀ ਕੰਧੀ ਤੋਣ ਵਾਕਫ ਨਹੀਣ ਹੋ ਸਕਦੇ ।",
              "additional_information": {}
            }
          }
        }
      },
      {
        "id": "87P0",
        "source_page": 24,
        "source_line": 7,
        "pronunciation": null,
        "pronunciation_information": null,
        "type": "Pankti",
        "gurmukhi": {
          "Dr. Ganda Singh": "goXw dr ieMqzwir qU cSmm s&yd Sud ["
        },
        "translations": {
          "English": {
            "Pritpal Singh Bindra": {
              "translation": "The dust of your street is like a collyrium for the eyes of those with divine sight,",
              "additional_information": {}
            }
          },
          "Punjabi": {
            "Dr. Ganda Singh": {
              "translation": "ਤੇਰੀ ਉਡੀਕ ਵਿਚ ਮੇਰੀਆਣ ਅੱਖਾਣ ਵੀ ਅੱਨ੍ਹੀਆਣ, ਚਿੱਟੀਆਣ, ਹੋ ਗਈਆਣ ਹਨ, ",
              "additional_information": {}
            }
          }
        }
      },
      {
        "id": "7RH6",
        "source_page": 24,
        "source_line": 7,
        "pronunciation": null,
        "pronunciation_information": null,
        "type": "Pankti",
        "gurmukhi": {
          "Dr. Ganda Singh": "mn cUM kunm ik by qU idlwsw nmI Svd [24[7["
        },
        "translations": {
          "English": {
            "Pritpal Singh Bindra": {
              "translation": "And for the tearful eyes, there is no other better cure than this. (41) (2)",
              "additional_information": {}
            }
          },
          "Punjabi": {
            "Dr. Ganda Singh": {
              "translation": "ਮੈਣ ਕੀ ਕਰਾਣ, ਕਿਉਣਕਿ ਤੇਰੇ ਬਿਨਾਣ ਮੇਰੀ ਢਾਰਸ ਨਹੀਣ ਹੋ ਸਕਦੀ ।",
              "additional_information": {}
            }
          }
        }
      }
    ]
  }
]
