{
  "content": [
    {
      "asset": "ssa2",
      "type": "primary",
      "data": "ਜਿਸ ਤੇ ਉਪਜਿਆ; ਤਿਸਹਿ ਪਛਾਨੁ ॥",
      "page": 825,
      "line": 13
    },
    {
      "asset": "sbms",
      "type": "translation",
      "language": "en",
      "data": "Recognise thou Him, O man, from whom thou hast sprung."
    },
    {
      "asset": "sbms",
      "type": "translation",
      "language": "pa",
      "data": "ਤੂੰ ਉਸ ਦੀ ਸਿੰਞਾਣ ਕਰ, ਹੇ ਬੰਦੇ! ਜਿਸ ਤੋਂ ਤੂੰ ਉਤਪੰਨ ਹੋਇਆ ਹੈ।"
    },
    {
      "asset": "dssk",
      "type": "translation",
      "language": "en",
      "data": "Acknowledge the One, from whom You originated."
    },
    {
      "asset": "nkft",
      "type": "translation",
      "language": "pa",
      "data": "ਜਿਸ ਵਾਹਿਗੁਰੂ ਤੇ ਮੈਂ ਉਪਜਿਆ ਥਾ ਅਬ ਗੁਰੋਂ ਦ੍ਵਾਰਾ ਤਿਸੀ ਕੋ ਪਹਿਚਾਨਿਆਂ ਹੈ॥"
    },
    {
      "asset": "psst",
      "type": "translation",
      "language": "pa",
      "data": "ਹੇ ਭਾਈ! ਜਿਸ ਪਰਮਾਤਮਾ ਤੋਂ ਤੂੰ ਪੈਦਾ ਹੋਇਆ ਹੈਂ, ਉਸ ਨਾਲ ਹੀ (ਸਦਾ) ਸਾਂਝ ਪਾਈ ਰੱਖ।"
    },
    {
      "asset": "snst",
      "type": "translation",
      "language": "es",
      "data": "Toma Conciencia de Él, de Quien te ha creado,"
    }
  ]
}